{
    "camera_angle_x": 0.6911112070083618,
    "frames": [
        {
            "file_path": "./train/r_0",
            "rotation": 0.06283185307179587,
            "transform_matrix": [
                [
                    -0.13912433385849,
                    -0.8847149610519409,
                    0.44485732913017273,
                    1.7933512926101685
                ],
                [
                    0.9902315735816956,
                    -0.12429959326982498,
                    0.06250102072954178,
                    0.25196006894111633
                ],
                [
                    0.0,
                    0.44924280047416687,
                    0.8933717608451843,
                    3.601445198059082
                ],
                [
                    0.0,
                    0.0,
                    0.0,
                    1.0
                ]
            ]
        },
        {
            "file_path": "./train/r_1",
            "rotation": 0.06283185307179587,
            "transform_matrix": [
                [
                    0.909648060798645,
                    -0.40793442726135254,
                    0.0778254047036171,
                    0.3137371838092804
                ],
                [
                    0.4152766168117523,
                    0.8935653567314148,
                    -0.17047366499900818,
                    -0.6872297525405884
                ],
                [
                    0.0,
                    0.18740496039390564,
                    0.9822419881820679,
                    3.959707736968994
                ],
                [
                    0.0,
                    0.0,
                    0.0,
                    1.0
                ]
            ]
        },
        {
            "file_path": "./train/r_2",
            "rotation": 0.06283185307179587,
            "transform_matrix": [
                [
                    -0.09199175983667374,
                    0.3931388854980469,
                    -0.9148266911506653,
                    -3.687936782836914
                ],
                [
                    -0.9957166910171509,
                    -0.036321114748716354,
                    0.08451853692531586,
                    0.34071919322013855
                ],
                [
                    0.0,
                    0.9187559485435486,
                    0.39479878544807434,
                    1.5915504693984985
                ],
                [
                    0.0,
                    0.0,
                    0.0,
                    1.0
                ]
            ]
        },
        {
            "file_path": "./train/r_3",
            "rotation": 0.06283185307179587,
            "transform_matrix": [
                [
                    -0.06314095854759216,
                    -0.8700748085975647,
                    0.48883047699928284,
                    1.9706201553344727
                ],
                [
                    0.9979615807533264,
                    -0.05504956841468811,
                    0.030928270891308784,
                    0.12468099594116211
                ],
                [
                    -1.862565213173184e-09,
                    0.489825576543808,
                    0.8717830181121826,
                    3.5144147872924805
                ],
                [
                    0.0,
                    0.0,
                    0.0,
                    1.0
                ]
            ]
        },
        {
            "file_path": "./train/r_4",
            "rotation": 0.06283185307179587,
            "transform_matrix": [
                [
                    0.999508261680603,
                    0.01648416370153427,
                    -0.025017090141773224,
                    -0.10085128992795944
                ],
                [
                    -0.029959309846162796,
                    0.5499478578567505,
                    -0.8346251249313354,
                    -3.3646206855773926
                ],
                [
                    -1.862565435217789e-09,
                    0.8350303173065186,
                    0.5501748323440552,
                    2.2179174423217773
                ],
                [
                    0.0,
                    0.0,
                    0.0,
                    1.0
                ]
            ]
        },
        {
            "file_path": "./train/r_5",
            "rotation": 0.06283185307179587,
            "transform_matrix": [
                [
                    -0.39262187480926514,
                    0.7712059617042542,
                    -0.5010483860969543,
                    -2.019874095916748
                ],
                [
                    -0.9196533560752869,
                    -0.3292461633682251,
                    0.21390947699546814,
                    0.8623322248458862
                ],
                [
                    0.0,
                    0.5448194742202759,
                    0.8385170102119446,
                    3.380309581756592
                ],
                [
                    0.0,
                    0.0,
                    0.0,
                    1.0
                ]
            ]
        },
        {
            "file_path": "./train/r_6",
            "rotation": 0.06283185307179587,
            "transform_matrix": [
                [
                    0.2507539391517639,
                    0.39160609245300293,
                    -0.8852657079696655,
                    -3.568767786026001
                ],
                [
                    -0.9680065512657166,
                    0.10144226998090744,
                    -0.22932061553001404,
                    -0.9244592189788818
                ],
                [
                    7.450260852692736e-09,
                    0.9145185351371765,
                    0.40451696515083313,
                    1.6307274103164673
                ],
                [
                    0.0,
                    0.0,
                    0.0,
                    1.0
                ]
            ]
        },
        {
            "file_path": "./train/r_7",
            "rotation": 0.06283185307179587,
            "transform_matrix": [
                [
                    -0.6812756657600403,
                    -0.29032108187675476,
                    0.6719368696212769,
                    2.7087762355804443
                ],
                [
                    0.7319684028625488,
                    -0.2702147960662842,
                    0.6254016757011414,
                    2.521178722381592
                ],
                [
                    1.4900521705385472e-08,
                    0.9179801940917969,
                    0.3965992331504822,
                    1.598808765411377
                ],
                [
                    0.0,
                    0.0,
                    0.0,
                    1.0
                ]
            ]
        },
        {
            "file_path": "./train/r_8",
            "rotation": 0.06283185307179587,
            "transform_matrix": [
                [
                    0.8745978474617004,
                    -0.3273557424545288,
                    0.3575468063354492,
                    1.441376805305481
                ],
                [
                    0.4847608506679535,
                    0.590610146522522,
                    -0.6450803875923157,
                    -2.6005094051361084
                ],
                [
                    0.0,
                    0.7375687956809998,
                    0.6752400398254395,
                    2.7220919132232666
                ],
                [
                    0.0,
                    0.0,
                    0.0,
                    1.0
                ]
            ]
        },
        {
            "file_path": "./train/r_9",
            "rotation": 0.06283185307179587,
            "transform_matrix": [
                [
                    -0.9586345553398132,
                    -0.10414130985736847,
                    0.26474466919898987,
                    1.0672639608383179
                ],
                [
                    0.2844892144203186,
                    -0.35092172026634216,
                    0.8921019434928894,
                    3.5963263511657715
                ],
                [
                    -7.450261740871156e-09,
                    0.9305902719497681,
                    0.36603525280952454,
                    1.4755961894989014
                ],
                [
                    0.0,
                    0.0,
                    0.0,
                    1.0
                ]
            ]
        },
        {
            "file_path": "./train/r_10",
            "rotation": 0.06283185307179587,
            "transform_matrix": [
                [
                    0.9434699416160583,
                    -0.2992255687713623,
                    0.142301544547081,
                    0.5736595392227173
                ],
                [
                    0.3313288390636444,
                    0.8520547151565552,
                    -0.4052083194255829,
                    -1.6335145235061646
                ],
                [
                    -1.4900521705385472e-08,
                    0.42948442697525024,
                    0.9030359387397766,
                    3.64040470123291
                ],
                [
                    0.0,
                    0.0,
                    0.0,
                    1.0
                ]
            ]
        },
        {
            "file_path": "./train/r_11",
            "rotation": 0.06283185307179587,
            "transform_matrix": [
                [
                    -0.9591361880302429,
                    0.2826261520385742,
                    -0.010030795820057392,
                    -0.04043710231781006
                ],
                [
                    -0.28279340267181396,
                    -0.9585689306259155,
                    0.03402094915509224,
                    0.13714849948883057
                ],
                [
                    -9.312827176088945e-10,
                    0.035469867289066315,
                    0.9993293881416321,
                    4.028592109680176
                ],
                [
                    0.0,
                    0.0,
                    0.0,
                    1.0
                ]
            ]
        },
        {
            "file_path": "./train/r_12",
            "rotation": 0.06283185307179587,
            "transform_matrix": [
                [
                    -0.7406004667282104,
                    0.34718459844589233,
                    -0.5752374529838562,
                    -2.3189523220062256
                ],
                [
                    -0.6718817949295044,
                    -0.38269391655921936,
                    0.6340715885162354,
                    2.5561296939849854
                ],
                [
                    0.0,
                    0.8561530709266663,
                    0.5166937708854675,
                    2.0829453468322754
                ],
                [
                    0.0,
                    0.0,
                    0.0,
                    1.0
                ]
            ]
        },
        {
            "file_path": "./train/r_13",
            "rotation": 0.06283185307179587,
            "transform_matrix": [
                [
                    0.6711605787277222,
                    0.24110780656337738,
                    -0.7009499669075012,
                    -2.8257358074188232
                ],
                [
                    -0.7412542104721069,
                    0.2183084487915039,
                    -0.6346675753593445,
                    -2.5585319995880127
                ],
                [
                    0.0,
                    0.9456207156181335,
                    0.32524439692497253,
                    1.3111560344696045
                ],
                [
                    0.0,
                    0.0,
                    0.0,
                    1.0
                ]
            ]
        },
        {
            "file_path": "./train/r_14",
            "rotation": 0.06283185307179587,
            "transform_matrix": [
                [
                    0.5517446994781494,
                    0.3963802754878998,
                    -0.733749508857727,
                    -2.957961082458496
                ],
                [
                    -0.8339617252349854,
                    0.2622430920600891,
                    -0.4854448139667511,
                    -1.956971526145935
                ],
                [
                    0.0,
                    0.8798303008079529,
                    0.47526028752326965,
                    1.9159146547317505
                ],
                [
                    0.0,
                    0.0,
                    0.0,
                    1.0
                ]
            ]
        },
        {
            "file_path": "./train/r_15",
            "rotation": 0.06283185307179587,
            "transform_matrix": [
                [
                    -0.058007948100566864,
                    -0.8273044228553772,
                    0.5587213039398193,
                    2.252370834350586
                ],
                [
                    0.9982731938362122,
                    -0.048073239624500275,
                    0.0324663370847702,
                    0.1308814138174057
                ],
                [
                    0.0,
                    0.5596840977668762,
                    0.8286698460578918,
                    3.3406131267547607
                ],
                [
                    0.0,
                    0.0,
                    0.0,
                    1.0
                ]
            ]
        },
        {
            "file_path": "./train/r_16",
            "rotation": 0.06283185307179587,
            "transform_matrix": [
                [
                    -0.20105114579200745,
                    0.137309268116951,
                    -0.9698676466941833,
                    -3.909822940826416
                ],
                [
                    -0.9795370697975159,
                    -0.02818288840353489,
                    0.19906646013259888,
                    0.8024957180023193
                ],
                [
                    -1.862565435217789e-09,
                    0.9901220798492432,
                    0.14016664028167725,
                    0.5650531649589539
                ],
                [
                    0.0,
                    0.0,
                    0.0,
                    1.0
                ]
            ]
        },
        {
            "file_path": "./train/r_17",
            "rotation": 0.06283185307179587,
            "transform_matrix": [
                [
                    0.7217222452163696,
                    0.44784849882125854,
                    -0.5277109742164612,
                    -2.127358913421631
                ],
                [
                    -0.6921206712722778,
                    0.46700266003608704,
                    -0.5502808690071106,
                    -2.2183446884155273
                ],
                [
                    -1.4900522593563892e-08,
                    0.7624499797821045,
                    0.6470158100128174,
                    2.608311891555786
                ],
                [
                    0.0,
                    0.0,
                    0.0,
                    1.0
                ]
            ]
        },
        {
            "file_path": "./train/r_18",
            "rotation": 0.06283185307179587,
            "transform_matrix": [
                [
                    -0.9978139400482178,
                    -0.011041860096156597,
                    0.06449510902166367,
                    0.2599988579750061
                ],
                [
                    0.0654333233833313,
                    -0.16838088631629944,
                    0.9835068583488464,
                    3.9648067951202393
                ],
                [
                    -9.312825510754408e-10,
                    0.9856551289558411,
                    0.16873641312122345,
                    0.6802263259887695
                ],
                [
                    0.0,
                    0.0,
                    0.0,
                    1.0
                ]
            ]
        },
        {
            "file_path": "./train/r_19",
            "rotation": 0.06283185307179587,
            "transform_matrix": [
                [
                    0.8759182691574097,
                    -0.3168765902519226,
                    0.3637012243270874,
                    1.4661870002746582
                ],
                [
                    0.48237043619155884,
                    0.5754042267799377,
                    -0.6604312658309937,
                    -2.66239333152771
                ],
                [
                    0.0,
                    0.7539822459220886,
                    0.6568633317947388,
                    2.648010015487671
                ],
                [
                    0.0,
                    0.0,
                    0.0,
                    1.0
                ]
            ]
        },
        {
            "file_path": "./train/r_20",
            "rotation": 0.06283185307179587,
            "transform_matrix": [
                [
                    0.986046314239502,
                    -0.036786362528800964,
                    0.16209183633327484,
                    0.653439998626709
                ],
                [
                    0.16621313989162445,
                    0.21823221445083618,
                    -0.9615970253944397,
                    -3.876481056213379
                ],
                [
                    -3.725130426346368e-09,
                    0.9751980304718018,
                    0.22130294144153595,
                    0.8921374082565308
                ],
                [
                    0.0,
                    0.0,
                    0.0,
                    1.0
                ]
            ]
        },
        {
            "file_path": "./train/r_21",
            "rotation": 0.06283185307179587,
            "transform_matrix": [
                [
                    -0.6292324066162109,
                    0.2937081456184387,
                    -0.7195306420326233,
                    -2.9006407260894775
                ],
                [
                    -0.7771618962287903,
                    -0.23780207335948944,
                    0.5825710892677307,
                    2.3485162258148193
                ],
                [
                    0.0,
                    0.9258378148078918,
                    0.3778940737247467,
                    1.5234026908874512
                ],
                [
                    0.0,
                    0.0,
                    0.0,
                    1.0
                ]
            ]
        },
        {
            "file_path": "./train/r_22",
            "rotation": 0.06283185307179587,
            "transform_matrix": [
                [
                    0.9904975295066833,
                    0.0960410088300705,
                    -0.09800871461629868,
                    -0.3951020836830139
                ],
                [
                    -0.13721826672554016,
                    0.6932632327079773,
                    -0.7074669599533081,
                    -2.85200834274292
                ],
                [
                    0.0,
                    0.714249312877655,
                    0.6998587250709534,
                    2.8213372230529785
                ],
                [
                    0.0,
                    0.0,
                    0.0,
                    1.0
                ]
            ]
        },
        {
            "file_path": "./train/r_23",
            "rotation": 0.06283185307179587,
            "transform_matrix": [
                [
                    0.9782507419586182,
                    0.09201278537511826,
                    -0.18567219376564026,
                    -0.7484995126724243
                ],
                [
                    -0.20721913874149323,
                    0.4343786835670471,
                    -0.8765308856964111,
                    -3.533554792404175
                ],
                [
                    0.0,
                    0.8960126638412476,
                    0.4440010190010071,
                    1.789899230003357
                ],
                [
                    0.0,
                    0.0,
                    0.0,
                    1.0
                ]
            ]
        },
        {
            "file_path": "./train/r_24",
            "rotation": 0.06283185307179587,
            "transform_matrix": [
                [
                    -0.9312132596969604,
                    0.11045322567224503,
                    -0.34721362590789795,
                    -1.3997206687927246
                ],
                [
                    -0.3643568158149719,
                    -0.2822933793067932,
                    0.8873991966247559,
                    3.5773682594299316
                ],
                [
                    0.0,
                    0.9529432058334351,
                    0.3031217157840729,
                    1.221973180770874
                ],
                [
                    0.0,
                    0.0,
                    0.0,
                    1.0
                ]
            ]
        },
        {
            "file_path": "./train/r_25",
            "rotation": 0.06283185307179587,
            "transform_matrix": [
                [
                    -0.3264584243297577,
                    -0.7766452431678772,
                    0.5387094020843506,
                    2.171696662902832
                ],
                [
                    0.9451661705970764,
                    -0.2682516276836395,
                    0.18606910109519958,
                    0.7500995397567749
                ],
                [
                    0.0,
                    0.5699588060379028,
                    0.8216373324394226,
                    3.312262773513794
                ],
                [
                    0.0,
                    0.0,
                    0.0,
                    1.0
                ]
            ]
        },
        {
            "file_path": "./train/r_26",
            "rotation": 0.06283185307179587,
            "transform_matrix": [
                [
                    0.18882696330547333,
                    -0.3954734802246094,
                    0.8988179564476013,
                    3.6234006881713867
                ],
                [
                    0.9819667935371399,
                    0.07604742795228958,
                    -0.17283788323402405,
                    -0.6967605948448181
                ],
                [
                    7.450261740871156e-09,
                    0.9153181910514832,
                    0.40270426869392395,
                    1.6234198808670044
                ],
                [
                    0.0,
                    0.0,
                    0.0,
                    1.0
                ]
            ]
        },
        {
            "file_path": "./train/r_27",
            "rotation": 0.06283185307179587,
            "transform_matrix": [
                [
                    -0.8122630715370178,
                    0.4397203326225281,
                    -0.38315021991729736,
                    -1.5445917844772339
                ],
                [
                    -0.5832177400588989,
                    -0.6124103665351868,
                    0.5336236357688904,
                    2.1511945724487305
                ],
                [
                    1.4900521705385472e-08,
                    0.656954824924469,
                    0.7538959383964539,
                    3.039177179336548
                ],
                [
                    0.0,
                    0.0,
                    0.0,
                    1.0
                ]
            ]
        },
        {
            "file_path": "./train/r_28",
            "rotation": 0.06283185307179587,
            "transform_matrix": [
                [
                    -0.9835481643676758,
                    0.02937569096684456,
                    -0.17800121009349823,
                    -0.7175754308700562
                ],
                [
                    -0.18040838837623596,
                    -0.16015000641345978,
                    0.9704245924949646,
                    3.9120683670043945
                ],
                [
                    1.862565213173184e-09,
                    0.986650288105011,
                    0.16281595826148987,
                    0.6563591957092285
                ],
                [
                    0.0,
                    0.0,
                    0.0,
                    1.0
                ]
            ]
        },
        {
            "file_path": "./train/r_29",
            "rotation": 0.06283185307179587,
            "transform_matrix": [
                [
                    -0.8483001589775085,
                    0.26280879974365234,
                    -0.45960670709609985,
                    -1.8528105020523071
                ],
                [
                    -0.5294345021247864,
                    -0.4210922122001648,
                    0.7364168167114258,
                    2.9687139987945557
                ],
                [
                    0.0,
                    0.8681030869483948,
                    0.4963558614253998,
                    2.0009572505950928
                ],
                [
                    0.0,
                    0.0,
                    0.0,
                    1.0
                ]
            ]
        },
        {
            "file_path": "./train/r_30",
            "rotation": 0.06283185307179587,
            "transform_matrix": [
                [
                    -0.8852792978286743,
                    -0.27226725220680237,
                    0.3769236207008362,
                    1.5194904804229736
                ],
                [
                    0.4649675190448761,
                    -0.5183857679367065,
                    0.7176472544670105,
                    2.893048048019409
                ],
                [
                    0.0,
                    0.8106396198272705,
                    0.5855154395103455,
                    2.3603858947753906
                ],
                [
                    0.0,
                    0.0,
                    0.0,
                    1.0
                ]
            ]
        },
        {
            "file_path": "./train/r_31",
            "rotation": 0.06283185307179587,
            "transform_matrix": [
                [
                    -0.5895698666572571,
                    -0.22450537979602814,
                    0.7758380174636841,
                    3.1276323795318604
                ],
                [
                    0.807664155960083,
                    -0.16388195753097534,
                    0.5663377642631531,
                    2.2830748558044434
                ],
                [
                    -1.4900519929028633e-08,
                    0.9605884552001953,
                    0.2779466509819031,
                    1.1204850673675537
                ],
                [
                    0.0,
                    0.0,
                    0.0,
                    1.0
                ]
            ]
        },
        {
            "file_path": "./train/r_32",
            "rotation": 0.06283185307179587,
            "transform_matrix": [
                [
                    -0.6871796250343323,
                    -0.20875069499015808,
                    0.6957918405532837,
                    2.8049423694610596
                ],
                [
                    0.7264283895492554,
                    -0.19747194647789001,
                    0.658198356628418,
                    2.6533920764923096
                ],
                [
                    0.0,
                    0.9578192830085754,
                    0.2873430848121643,
                    1.1583648920059204
                ],
                [
                    0.0,
                    0.0,
                    0.0,
                    1.0
                ]
            ]
        },
        {
            "file_path": "./train/r_33",
            "rotation": 0.06283185307179587,
            "transform_matrix": [
                [
                    0.33186203241348267,
                    0.8596189618110657,
                    -0.3884499967098236,
                    -1.565956711769104
                ],
                [
                    -0.943282425403595,
                    0.30242788791656494,
                    -0.13666300475597382,
                    -0.5509289503097534
                ],
                [
                    0.0,
                    0.4118040204048157,
                    0.9112338423728943,
                    3.673452854156494
                ],
                [
                    0.0,
                    0.0,
                    0.0,
                    1.0
                ]
            ]
        },
        {
            "file_path": "./train/r_34",
            "rotation": 0.06283185307179587,
            "transform_matrix": [
                [
                    -0.18997949361801147,
                    0.6515393257141113,
                    -0.7344059944152832,
                    -2.9606077671051025
                ],
                [
                    -0.9817442893981934,
                    -0.12608081102371216,
                    0.1421165019273758,
                    0.572913646697998
                ],
                [
                    -7.450261296781946e-09,
                    0.7480574250221252,
                    0.6636022329330444,
                    2.6751768589019775
                ],
                [
                    0.0,
                    0.0,
                    0.0,
                    1.0
                ]
            ]
        },
        {
            "file_path": "./train/r_35",
            "rotation": 0.06283185307179587,
            "transform_matrix": [
                [
                    -0.8993507623672485,
                    0.20702297985553741,
                    -0.38500332832336426,
                    -1.5520621538162231
                ],
                [
                    -0.4371296763420105,
                    -0.42592915892601013,
                    0.792106032371521,
                    3.19321346282959
                ],
                [
                    0.0,
                    0.8807472586631775,
                    0.4735587239265442,
                    1.9090551137924194
                ],
                [
                    0.0,
                    0.0,
                    0.0,
                    1.0
                ]
            ]
        },
        {
            "file_path": "./train/r_36",
            "rotation": 0.06283185307179587,
            "transform_matrix": [
                [
                    -0.013946273364126682,
                    0.6000896692276001,
                    -0.7997758984565735,
                    -3.224132776260376
                ],
                [
                    -0.9998599290847778,
                    -0.00837018620222807,
                    0.011155455373227596,
                    0.04497093707323074
                ],
                [
                    0.0,
                    0.799882709980011,
                    0.6001262664794922,
                    2.4192862510681152
                ],
                [
                    0.0,
                    0.0,
                    0.0,
                    1.0
                ]
            ]
        },
        {
            "file_path": "./train/r_37",
            "rotation": 0.06283185307179587,
            "transform_matrix": [
                [
                    0.9519575834274292,
                    0.2997687757015228,
                    -0.061940718442201614,
                    -0.24970132112503052
                ],
                [
                    -0.3060901165008545,
                    0.9322977662086487,
                    -0.19263914227485657,
                    -0.7765852212905884
                ],
                [
                    -3.725130870435578e-09,
                    0.20235978066921234,
                    0.9792706370353699,
                    3.9477291107177734
                ],
                [
                    0.0,
                    0.0,
                    0.0,
                    1.0
                ]
            ]
        },
        {
            "file_path": "./train/r_38",
            "rotation": 0.06283185307179587,
            "transform_matrix": [
                [
                    0.12166322767734528,
                    -0.4689236879348755,
                    0.87478107213974,
                    3.526500940322876
                ],
                [
                    0.9925281405448914,
                    0.05748025327920914,
                    -0.10722988098859787,
                    -0.43227535486221313
                ],
                [
                    -3.725130648390973e-09,
                    0.881360650062561,
                    0.47241634130477905,
                    1.9044498205184937
                ],
                [
                    0.0,
                    0.0,
                    0.0,
                    1.0
                ]
            ]
        },
        {
            "file_path": "./train/r_39",
            "rotation": 0.06283185307179587,
            "transform_matrix": [
                [
                    0.9776189923286438,
                    -0.044666800647974014,
                    0.20537911355495453,
                    0.8279438614845276
                ],
                [
                    0.21017949283123016,
                    0.2077610343694687,
                    -0.955290675163269,
                    -3.8510589599609375
                ],
                [
                    3.725130648390973e-09,
                    0.9771541953086853,
                    0.21250055730342865,
                    0.8566524982452393
                ],
                [
                    0.0,
                    0.0,
                    0.0,
                    1.0
                ]
            ]
        },
        {
            "file_path": "./train/r_40",
            "rotation": 0.06283185307179587,
            "transform_matrix": [
                [
                    0.9671311974525452,
                    0.15603777766227722,
                    -0.2005634754896164,
                    -0.8085306882858276
                ],
                [
                    -0.25410929322242737,
                    0.5938743352890015,
                    -0.7633376717567444,
                    -3.077239990234375
                ],
                [
                    -7.450261296781946e-09,
                    0.7892752885818481,
                    0.6140090227127075,
                    2.4752519130706787
                ],
                [
                    0.0,
                    0.0,
                    0.0,
                    1.0
                ]
            ]
        },
        {
            "file_path": "./train/r_41",
            "rotation": 0.06283185307179587,
            "transform_matrix": [
                [
                    0.9995883107185364,
                    0.024793483316898346,
                    -0.011076586320996284,
                    -0.044652990996837616
                ],
                [
                    -0.027154380455613136,
                    0.912680447101593,
                    -0.4077436029911041,
                    -1.6437349319458008
                ],
                [
                    0.0,
                    0.40790873765945435,
                    0.9129840135574341,
                    3.6805083751678467
                ],
                [
                    0.0,
                    0.0,
                    0.0,
                    1.0
                ]
            ]
        },
        {
            "file_path": "./train/r_42",
            "rotation": 0.06283185307179587,
            "transform_matrix": [
                [
                    -0.3469982147216797,
                    -0.7027133107185364,
                    0.6210789680480957,
                    2.5037527084350586
                ],
                [
                    0.9378200769424438,
                    -0.26000750064849854,
                    0.22980239987373352,
                    0.9264013171195984
                ],
                [
                    0.0,
                    0.662253737449646,
                    0.749245822429657,
                    3.0204310417175293
                ],
                [
                    0.0,
                    0.0,
                    0.0,
                    1.0
                ]
            ]
        },
        {
            "file_path": "./train/r_43",
            "rotation": 0.06283185307179587,
            "transform_matrix": [
                [
                    -0.6765615344047546,
                    0.6366124749183655,
                    -0.37004658579826355,
                    -1.4917670488357544
                ],
                [
                    -0.7363279461860657,
                    -0.5849397778511047,
                    0.34001052379608154,
                    1.3706828355789185
                ],
                [
                    -2.9801043410770944e-08,
                    0.502553403377533,
                    0.8645090460777283,
                    3.485091209411621
                ],
                [
                    0.0,
                    0.0,
                    0.0,
                    1.0
                ]
            ]
        },
        {
            "file_path": "./train/r_44",
            "rotation": 0.06283185307179587,
            "transform_matrix": [
                [
                    -0.933687686920166,
                    -0.17305977642536163,
                    0.3133598268032074,
                    1.2632458209991455
                ],
                [
                    0.3579685389995575,
                    -0.4513910412788391,
                    0.8173350691795349,
                    3.2949185371398926
                ],
                [
                    0.0,
                    0.8753778338432312,
                    0.48341143131256104,
                    1.9487740993499756
                ],
                [
                    0.0,
                    0.0,
                    0.0,
                    1.0
                ]
            ]
        },
        {
            "file_path": "./train/r_45",
            "rotation": 0.06283185307179587,
            "transform_matrix": [
                [
                    0.8076444864273071,
                    -0.1807355135679245,
                    0.561215341091156,
                    2.2624247074127197
                ],
                [
                    0.5895968079566956,
                    0.247576043009758,
                    -0.7687667608261108,
                    -3.099125862121582
                ],
                [
                    0.0,
                    0.9518564343452454,
                    0.3065165877342224,
                    1.235658884048462
                ],
                [
                    0.0,
                    0.0,
                    0.0,
                    1.0
                ]
            ]
        },
        {
            "file_path": "./train/r_46",
            "rotation": 0.06283185307179587,
            "transform_matrix": [
                [
                    0.6893812417984009,
                    0.302700400352478,
                    -0.6580642461776733,
                    -2.6528513431549072
                ],
                [
                    -0.724339485168457,
                    0.28809139132499695,
                    -0.626304566860199,
                    -2.5248186588287354
                ],
                [
                    0.0,
                    0.9084964394569397,
                    0.41786542534828186,
                    1.6845389604568481
                ],
                [
                    0.0,
                    0.0,
                    0.0,
                    1.0
                ]
            ]
        },
        {
            "file_path": "./train/r_47",
            "rotation": 0.06283185307179587,
            "transform_matrix": [
                [
                    0.9959983825683594,
                    -0.01751047559082508,
                    0.0871482565999031,
                    0.3513202965259552
                ],
                [
                    0.08888973295688629,
                    0.19620268046855927,
                    -0.9764853119850159,
                    -3.936500072479248
                ],
                [
                    1.862564991128579e-09,
                    0.9804018139839172,
                    0.19697542488574982,
                    0.7940659523010254
                ],
                [
                    0.0,
                    0.0,
                    0.0,
                    1.0
                ]
            ]
        },
        {
            "file_path": "./train/r_48",
            "rotation": 0.06283185307179587,
            "transform_matrix": [
                [
                    -0.37327149510383606,
                    0.5706121921539307,
                    -0.7314443588256836,
                    -2.9486680030822754
                ],
                [
                    -0.9276759624481201,
                    -0.2295987755060196,
                    0.2943132817745209,
                    1.186463713645935
                ],
                [
                    0.0,
                    0.7884644865989685,
                    0.6150498986244202,
                    2.479447841644287
                ],
                [
                    0.0,
                    0.0,
                    0.0,
                    1.0
                ]
            ]
        },
        {
            "file_path": "./train/r_49",
            "rotation": 0.06283185307179587,
            "transform_matrix": [
                [
                    -0.48666611313819885,
                    0.2649073898792267,
                    -0.8324072360992432,
                    -3.355679512023926
                ],
                [
                    -0.8735388517379761,
                    -0.14758525788784027,
                    0.4637508690357208,
                    1.8695168495178223
                ],
                [
                    -7.450260408603526e-09,
                    0.9529075026512146,
                    0.30323368310928345,
                    1.2224245071411133
                ],
                [
                    0.0,
                    0.0,
                    0.0,
                    1.0
                ]
            ]
        },
        {
            "file_path": "./train/r_50",
            "rotation": 0.06283185307179587,
            "transform_matrix": [
                [
                    -0.842268168926239,
                    0.42667248845100403,
                    -0.32933783531188965,
                    -1.3276580572128296
                ],
                [
                    -0.5389792323112488,
                    -0.6667652130126953,
                    0.5146594047546387,
                    2.0747439861297607
                ],
                [
                    0.0,
                    0.6110358238220215,
                    0.7915679216384888,
                    3.1910440921783447
                ],
                [
                    0.0,
                    0.0,
                    0.0,
                    1.0
                ]
            ]
        },
        {
            "file_path": "./train/r_51",
            "rotation": 0.06283185307179587,
            "transform_matrix": [
                [
                    0.7785264849662781,
                    0.13437379896640778,
                    -0.6129902005195618,
                    -2.471144676208496
                ],
                [
                    -0.6275433897972107,
                    0.16670329868793488,
                    -0.7604718208312988,
                    -3.0656867027282715
                ],
                [
                    0.0,
                    0.9768027663230896,
                    0.21410971879959106,
                    0.8631395697593689
                ],
                [
                    0.0,
                    0.0,
                    0.0,
                    1.0
                ]
            ]
        },
        {
            "file_path": "./train/r_52",
            "rotation": 0.06283185307179587,
            "transform_matrix": [
                [
                    0.9990274310112,
                    0.04181400686502457,
                    -0.010495719499886036,
                    -0.04231134429574013
                ],
                [
                    -0.04310961440205574,
                    0.969002902507782,
                    -0.24322910606861115,
                    -0.9805282950401306
                ],
                [
                    -9.312826620977432e-10,
                    0.24346427619457245,
                    0.9698695540428162,
                    3.909830331802368
                ],
                [
                    0.0,
                    0.0,
                    0.0,
                    1.0
                ]
            ]
        },
        {
            "file_path": "./train/r_53",
            "rotation": 0.06283185307179587,
            "transform_matrix": [
                [
                    0.6479671001434326,
                    -0.3858264982700348,
                    0.6566607356071472,
                    2.647193670272827
                ],
                [
                    0.7616119980812073,
                    0.32825493812561035,
                    -0.5586763024330139,
                    -2.2521893978118896
                ],
                [
                    0.0,
                    0.8621928095817566,
                    0.5065518617630005,
                    2.042060375213623
                ],
                [
                    0.0,
                    0.0,
                    0.0,
                    1.0
                ]
            ]
        },
        {
            "file_path": "./train/r_54",
            "rotation": 0.06283185307179587,
            "transform_matrix": [
                [
                    -0.8649480938911438,
                    -0.141237273812294,
                    0.481490820646286,
                    1.9410316944122314
                ],
                [
                    0.5017760396003723,
                    -0.243461012840271,
                    0.8299810290336609,
                    3.3458986282348633
                ],
                [
                    -7.450261740871156e-09,
                    0.9595669507980347,
                    0.2814524173736572,
                    1.134617805480957
                ],
                [
                    0.0,
                    0.0,
                    0.0,
                    1.0
                ]
            ]
        },
        {
            "file_path": "./train/r_55",
            "rotation": 0.06283185307179587,
            "transform_matrix": [
                [
                    -0.6961765289306641,
                    -0.6619155406951904,
                    0.27776557207107544,
                    1.1197550296783447
                ],
                [
                    0.717810869216919,
                    -0.6419658660888672,
                    0.2693939208984375,
                    1.0860064029693604
                ],
                [
                    0.0,
                    0.3869594931602478,
                    0.9220578074455261,
                    3.717087507247925
                ],
                [
                    0.0,
                    0.0,
                    0.0,
                    1.0
                ]
            ]
        },
        {
            "file_path": "./train/r_56",
            "rotation": 0.06283185307179587,
            "transform_matrix": [
                [
                    -0.9671654105186462,
                    0.07676290720701218,
                    -0.24210205674171448,
                    -0.9759849309921265
                ],
                [
                    -0.253978967666626,
                    -0.2923172414302826,
                    0.9219374656677246,
                    3.716602325439453
                ],
                [
                    0.0,
                    0.9532303810119629,
                    0.3022172451019287,
                    1.2183270454406738
                ],
                [
                    0.0,
                    0.0,
                    0.0,
                    1.0
                ]
            ]
        },
        {
            "file_path": "./train/r_57",
            "rotation": 0.06283185307179587,
            "transform_matrix": [
                [
                    -0.9283649325370789,
                    0.07822917401790619,
                    -0.36322706937789917,
                    -1.464275598526001
                ],
                [
                    -0.37155458331108093,
                    -0.19546310603618622,
                    0.9075577855110168,
                    3.6586334705352783
                ],
                [
                    7.450261296781946e-09,
                    0.9775808453559875,
                    0.2105288952589035,
                    0.8487042188644409
                ],
                [
                    0.0,
                    0.0,
                    0.0,
                    1.0
                ]
            ]
        },
        {
            "file_path": "./train/r_58",
            "rotation": 0.06283185307179587,
            "transform_matrix": [
                [
                    0.8381223678588867,
                    -0.29434847831726074,
                    0.4591638445854187,
                    1.851025104522705
                ],
                [
                    0.5454037189483643,
                    0.4523254930973053,
                    -0.7055973410606384,
                    -2.8444714546203613
                ],
                [
                    -1.4900523481742312e-08,
                    0.8418731093406677,
                    0.5396464467048645,
                    2.175474166870117
                ],
                [
                    0.0,
                    0.0,
                    0.0,
                    1.0
                ]
            ]
        },
        {
            "file_path": "./train/r_59",
            "rotation": 0.06283185307179587,
            "transform_matrix": [
                [
                    0.44176799058914185,
                    -0.6114111542701721,
                    0.6564764976501465,
                    2.6464507579803467
                ],
                [
                    0.8970814943313599,
                    0.3010895550251007,
                    -0.32328200340270996,
                    -1.3032453060150146
                ],
                [
                    0.0,
                    0.7317865490913391,
                    0.6815018653869629,
                    2.747335195541382
                ],
                [
                    0.0,
                    0.0,
                    0.0,
                    1.0
                ]
            ]
        },
        {
            "file_path": "./train/r_60",
            "rotation": 0.06283185307179587,
            "transform_matrix": [
                [
                    0.5974479913711548,
                    0.5763065814971924,
                    -0.5575544834136963,
                    -2.247666835784912
                ],
                [
                    -0.801854133605957,
                    0.4293963313102722,
                    -0.4154244661331177,
                    -1.6746987104415894
                ],
                [
                    1.4900520817207052e-08,
                    0.6953269839286804,
                    0.7186605930328369,
                    2.8971328735351562
                ],
                [
                    0.0,
                    0.0,
                    0.0,
                    1.0
                ]
            ]
        },
        {
            "file_path": "./train/r_61",
            "rotation": 0.06283185307179587,
            "transform_matrix": [
                [
                    -0.999889075756073,
                    -0.00546695850789547,
                    0.010294864885509014,
                    0.041501644998788834
                ],
                [
                    0.011656297370791435,
                    -0.46896129846572876,
                    0.8831040263175964,
                    3.5600533485412598
                ],
                [
                    0.0,
                    0.8831961750984192,
                    0.46897611021995544,
                    1.8905812501907349
                ],
                [
                    0.0,
                    0.0,
                    0.0,
                    1.0
                ]
            ]
        },
        {
            "file_path": "./train/r_62",
            "rotation": 0.06283185307179587,
            "transform_matrix": [
                [
                    0.9996087551116943,
                    -0.017945170402526855,
                    0.019355054944753647,
                    0.0780259445309639
                ],
                [
                    0.026393594220280647,
                    0.6796402931213379,
                    -0.7330371737480164,
                    -2.9550890922546387
                ],
                [
                    9.312827176088945e-10,
                    0.733319103717804,
                    0.6798526048660278,
                    2.7406864166259766
                ],
                [
                    0.0,
                    0.0,
                    0.0,
                    1.0
                ]
            ]
        },
        {
            "file_path": "./train/r_63",
            "rotation": 0.06283185307179587,
            "transform_matrix": [
                [
                    0.1557258665561676,
                    0.21659082174301147,
                    -0.9637212157249451,
                    -3.885045051574707
                ],
                [
                    -0.9877569675445557,
                    0.034146860241889954,
                    -0.15193650126457214,
                    -0.6125009059906006
                ],
                [
                    0.0,
                    0.9756598472595215,
                    0.21925809979438782,
                    0.8838942050933838
                ],
                [
                    0.0,
                    0.0,
                    0.0,
                    1.0
                ]
            ]
        },
        {
            "file_path": "./train/r_64",
            "rotation": 0.06283185307179587,
            "transform_matrix": [
                [
                    0.9698668718338013,
                    -0.08736735582351685,
                    0.22724419832229614,
                    0.9160885214805603
                ],
                [
                    0.24345886707305908,
                    0.3480452299118042,
                    -0.9052724838256836,
                    -3.649420738220215
                ],
                [
                    0.0,
                    0.9333924055099487,
                    0.3588303029537201,
                    1.446550965309143
                ],
                [
                    0.0,
                    0.0,
                    0.0,
                    1.0
                ]
            ]
        },
        {
            "file_path": "./train/r_65",
            "rotation": 0.06283185307179587,
            "transform_matrix": [
                [
                    -0.29925453662872314,
                    0.9301917552947998,
                    -0.21253187954425812,
                    -0.8567787408828735
                ],
                [
                    -0.9541283249855042,
                    -0.2917470335960388,
                    0.06665889173746109,
                    0.26872166991233826
                ],
                [
                    3.725130648390973e-09,
                    0.22274821996688843,
                    0.9748354554176331,
                    3.929849624633789
                ],
                [
                    0.0,
                    0.0,
                    0.0,
                    1.0
                ]
            ]
        },
        {
            "file_path": "./train/r_66",
            "rotation": 0.06283185307179587,
            "transform_matrix": [
                [
                    0.7195260524749756,
                    -0.42718231678009033,
                    0.5474728345870972,
                    2.207024574279785
                ],
                [
                    0.6944037079811096,
                    0.4426370859146118,
                    -0.5672794580459595,
                    -2.2868709564208984
                ],
                [
                    -1.4900523481742312e-08,
                    0.7884018421173096,
                    0.6151300072669983,
                    2.4797706604003906
                ],
                [
                    0.0,
                    0.0,
                    0.0,
                    1.0
                ]
            ]
        },
        {
            "file_path": "./train/r_67",
            "rotation": 0.06283185307179587,
            "transform_matrix": [
                [
                    0.42503026127815247,
                    -0.12598131597042084,
                    0.8963236212730408,
                    3.613345146179199
                ],
                [
                    0.9051317572593689,
                    0.0591580905020237,
                    -0.4208940863609314,
                    -1.6967483758926392
                ],
                [
                    -3.725130870435578e-09,
                    0.9902620911598206,
                    0.13917459547519684,
                    0.5610538721084595
                ],
                [
                    0.0,
                    0.0,
                    0.0,
                    1.0
                ]
            ]
        },
        {
            "file_path": "./train/r_68",
            "rotation": 0.06283185307179587,
            "transform_matrix": [
                [
                    0.7012135982513428,
                    0.1993769407272339,
                    -0.684446394443512,
                    -2.7592058181762695
                ],
                [
                    -0.7128909826278687,
                    0.19611108303070068,
                    -0.6732349395751953,
                    -2.7140090465545654
                ],
                [
                    0.0,
                    0.9600932002067566,
                    0.2796516418457031,
                    1.1273584365844727
                ],
                [
                    0.0,
                    0.0,
                    0.0,
                    1.0
                ]
            ]
        },
        {
            "file_path": "./train/r_69",
            "rotation": 0.06283185307179587,
            "transform_matrix": [
                [
                    -0.6265134215354919,
                    0.7642797231674194,
                    -0.152695894241333,
                    -0.6155622601509094
                ],
                [
                    -0.7793557047843933,
                    -0.6143940091133118,
                    0.12275014817714691,
                    0.49484214186668396
                ],
                [
                    7.450261740871156e-09,
                    0.19592460989952087,
                    0.9805782437324524,
                    3.953000783920288
                ],
                [
                    0.0,
                    0.0,
                    0.0,
                    1.0
                ]
            ]
        },
        {
            "file_path": "./train/r_70",
            "rotation": 0.06283185307179587,
            "transform_matrix": [
                [
                    0.7875994443893433,
                    0.3199637830257416,
                    -0.5265293717384338,
                    -2.1225953102111816
                ],
                [
                    -0.6161179542541504,
                    0.409017950296402,
                    -0.6730760931968689,
                    -2.7133681774139404
                ],
                [
                    0.0,
                    0.8545861840248108,
                    0.5192812085151672,
                    2.0933756828308105
                ],
                [
                    0.0,
                    0.0,
                    0.0,
                    1.0
                ]
            ]
        },
        {
            "file_path": "./train/r_71",
            "rotation": 0.06283185307179587,
            "transform_matrix": [
                [
                    0.7598172426223755,
                    -0.25727444887161255,
                    0.5969991087913513,
                    2.40667986869812
                ],
                [
                    0.6500706672668457,
                    0.3007081151008606,
                    -0.6977859139442444,
                    -2.812981367111206
                ],
                [
                    0.0,
                    0.9183542132377625,
                    0.39573240280151367,
                    1.5953142642974854
                ],
                [
                    0.0,
                    0.0,
                    0.0,
                    1.0
                ]
            ]
        },
        {
            "file_path": "./train/r_72",
            "rotation": 0.06283185307179587,
            "transform_matrix": [
                [
                    -0.1476244032382965,
                    0.7763293981552124,
                    -0.6127648949623108,
                    -2.47023606300354
                ],
                [
                    -0.9890002012252808,
                    -0.11587981134653091,
                    0.09146515280008316,
                    0.3687230348587036
                ],
                [
                    7.450261740871156e-09,
                    0.6195758581161499,
                    0.7849018573760986,
                    3.164170980453491
                ],
                [
                    0.0,
                    0.0,
                    0.0,
                    1.0
                ]
            ]
        },
        {
            "file_path": "./train/r_73",
            "rotation": 0.06283185307179587,
            "transform_matrix": [
                [
                    0.9889739751815796,
                    0.13652648031711578,
                    -0.05662666633725166,
                    -0.22827880084514618
                ],
                [
                    -0.1477992981672287,
                    0.913543701171875,
                    -0.3789077401161194,
                    -1.5274888277053833
                ],
                [
                    -3.725129982257158e-09,
                    0.38312968611717224,
                    0.9236556887626648,
                    3.7235286235809326
                ],
                [
                    0.0,
                    0.0,
                    0.0,
                    1.0
                ]
            ]
        },
        {
            "file_path": "./train/r_74",
            "rotation": 0.06283185307179587,
            "transform_matrix": [
                [
                    -0.1571987271308899,
                    -0.44621598720550537,
                    0.8809719681739807,
                    3.5514583587646484
                ],
                [
                    0.98752361536026,
                    -0.07103079557418823,
                    0.14023733139038086,
                    0.565338134765625
                ],
                [
                    0.0,
                    0.8920964002609253,
                    0.45181769132614136,
                    1.8214105367660522
                ],
                [
                    0.0,
                    0.0,
                    0.0,
                    1.0
                ]
            ]
        },
        {
            "file_path": "./train/r_75",
            "rotation": 0.06283185307179587,
            "transform_matrix": [
                [
                    -0.028605587780475616,
                    -0.36107975244522095,
                    0.9320568442344666,
                    3.7573964595794678
                ],
                [
                    0.9995478391647339,
                    -0.010333570651710033,
                    0.026674093678593636,
                    0.10753115266561508
                ],
                [
                    0.0,
                    0.9324722290039062,
                    0.36121445894241333,
                    1.4561622142791748
                ],
                [
                    0.0,
                    0.0,
                    0.0,
                    1.0
                ]
            ]
        },
        {
            "file_path": "./train/r_76",
            "rotation": 0.06283185307179587,
            "transform_matrix": [
                [
                    0.07634740322828293,
                    -0.5011908411979675,
                    0.8619248867034912,
                    3.4746735095977783
                ],
                [
                    0.9970383048057556,
                    0.038378287106752396,
                    -0.06600120663642883,
                    -0.26607033610343933
                ],
                [
                    -3.725130870435578e-09,
                    0.8644794225692749,
                    0.502639889717102,
                    2.026289939880371
                ],
                [
                    0.0,
                    0.0,
                    0.0,
                    1.0
                ]
            ]
        },
        {
            "file_path": "./train/r_77",
            "rotation": 0.06283185307179587,
            "transform_matrix": [
                [
                    0.25346457958221436,
                    -0.34110069274902344,
                    0.9051693677902222,
                    3.649005174636841
                ],
                [
                    0.9673004150390625,
                    0.08937962353229523,
                    -0.23718421161174774,
                    -0.9561596512794495
                ],
                [
                    7.450261740871156e-09,
                    0.9357624650001526,
                    0.3526037037372589,
                    1.4214497804641724
                ],
                [
                    0.0,
                    0.0,
                    0.0,
                    1.0
                ]
            ]
        },
        {
            "file_path": "./train/r_78",
            "rotation": 0.06283185307179587,
            "transform_matrix": [
                [
                    -0.032165758311748505,
                    -0.9719617366790771,
                    0.2328987717628479,
                    0.9388837814331055
                ],
                [
                    0.999439537525177,
                    -0.03128141909837723,
                    0.007495567202568054,
                    0.030216846615076065
                ],
                [
                    0.0,
                    0.2330278605222702,
                    0.9724295735359192,
                    3.9201509952545166
                ],
                [
                    0.0,
                    0.0,
                    0.0,
                    1.0
                ]
            ]
        },
        {
            "file_path": "./train/r_79",
            "rotation": 0.06283185307179587,
            "transform_matrix": [
                [
                    0.00875947531312704,
                    -0.4603886902332306,
                    0.8876363635063171,
                    3.578324317932129
                ],
                [
                    0.9999187588691711,
                    0.004033091012388468,
                    -0.007775860372930765,
                    -0.03134679049253464
                ],
                [
                    -2.328206655244358e-10,
                    0.8877025842666626,
                    0.4603896737098694,
                    1.8559668064117432
                ],
                [
                    0.0,
                    0.0,
                    0.0,
                    1.0
                ]
            ]
        },
        {
            "file_path": "./train/r_80",
            "rotation": 0.06283185307179587,
            "transform_matrix": [
                [
                    0.9325047135353088,
                    -0.11306110769510269,
                    0.3428817093372345,
                    1.3822574615478516
                ],
                [
                    0.36103925108909607,
                    0.2920181453227997,
                    -0.8856067657470703,
                    -3.5701422691345215
                ],
                [
                    0.0,
                    0.9497013092041016,
                    0.31312984228134155,
                    1.262318730354309
                ],
                [
                    0.0,
                    0.0,
                    0.0,
                    1.0
                ]
            ]
        },
        {
            "file_path": "./train/r_81",
            "rotation": 0.06283185307179587,
            "transform_matrix": [
                [
                    -0.9719275832176208,
                    0.03922237083315849,
                    -0.23180338740348816,
                    -0.9344678521156311
                ],
                [
                    -0.23509766161441803,
                    -0.16215093433856964,
                    0.9583086371421814,
                    3.863224744796753
                ],
                [
                    0.0,
                    0.9859809875488281,
                    0.1668211668729782,
                    0.6725053191184998
                ],
                [
                    0.0,
                    0.0,
                    0.0,
                    1.0
                ]
            ]
        },
        {
            "file_path": "./train/r_82",
            "rotation": 0.06283185307179587,
            "transform_matrix": [
                [
                    0.06113699823617935,
                    0.8464875817298889,
                    -0.5288577079772949,
                    -2.13198184967041
                ],
                [
                    -0.9980863332748413,
                    0.051850929856300354,
                    -0.03239476680755615,
                    -0.13059286773204803
                ],
                [
                    -1.8625651021508816e-09,
                    0.5298681259155273,
                    0.8480432629585266,
                    3.418713092803955
                ],
                [
                    0.0,
                    0.0,
                    0.0,
                    1.0
                ]
            ]
        },
        {
            "file_path": "./train/r_83",
            "rotation": 0.06283185307179587,
            "transform_matrix": [
                [
                    -0.7998042106628418,
                    0.1564628630876541,
                    -0.5794392228126526,
                    -2.335890769958496
                ],
                [
                    -0.6001896262168884,
                    -0.20850016176700592,
                    0.7721524834632874,
                    3.1127748489379883
                ],
                [
                    7.450261740871156e-09,
                    0.9654206037521362,
                    0.26066839694976807,
                    1.0508313179016113
                ],
                [
                    0.0,
                    0.0,
                    0.0,
                    1.0
                ]
            ]
        },
        {
            "file_path": "./train/r_84",
            "rotation": 0.06283185307179587,
            "transform_matrix": [
                [
                    0.4005568027496338,
                    -0.6599482893943787,
                    0.6355870366096497,
                    2.562238931655884
                ],
                [
                    0.916225016117096,
                    0.2885172963142395,
                    -0.27786698937416077,
                    -1.120163917541504
                ],
                [
                    -1.4900522593563892e-08,
                    0.6936972141265869,
                    0.7202335596084595,
                    2.9034743309020996
                ],
                [
                    0.0,
                    0.0,
                    0.0,
                    1.0
                ]
            ]
        },
        {
            "file_path": "./train/r_85",
            "rotation": 0.06283185307179587,
            "transform_matrix": [
                [
                    0.9973809123039246,
                    0.054273542016744614,
                    -0.04690816253423691,
                    -0.18910063803195953
                ],
                [
                    -0.0717339739203453,
                    0.7546130418777466,
                    -0.6522057056427002,
                    -2.6292335987091064
                ],
                [
                    -3.725130648390973e-09,
                    0.6539139747619629,
                    0.7565348148345947,
                    3.0498151779174805
                ],
                [
                    0.0,
                    0.0,
                    0.0,
                    1.0
                ]
            ]
        },
        {
            "file_path": "./train/r_86",
            "rotation": 0.06283185307179587,
            "transform_matrix": [
                [
                    0.16411258280277252,
                    -0.8643861413002014,
                    0.4752633273601532,
                    1.9159268140792847
                ],
                [
                    0.9863980412483215,
                    0.14381277561187744,
                    -0.07907222956418991,
                    -0.31876349449157715
                ],
                [
                    0.0,
                    0.4818136990070343,
                    0.8762362003326416,
                    3.5323667526245117
                ],
                [
                    0.0,
                    0.0,
                    0.0,
                    1.0
                ]
            ]
        },
        {
            "file_path": "./train/r_87",
            "rotation": 0.06283185307179587,
            "transform_matrix": [
                [
                    0.9907426834106445,
                    0.07417536526918411,
                    -0.11332042515277863,
                    -0.45682811737060547
                ],
                [
                    -0.1354365050792694,
                    0.5426062941551208,
                    -0.828959584236145,
                    -3.3417809009552
                ],
                [
                    0.0,
                    0.8366994857788086,
                    0.5476329922676086,
                    2.2076704502105713
                ],
                [
                    0.0,
                    0.0,
                    0.0,
                    1.0
                ]
            ]
        },
        {
            "file_path": "./train/r_88",
            "rotation": 0.06283185307179587,
            "transform_matrix": [
                [
                    0.9996252059936523,
                    -0.01713254302740097,
                    0.01923595555126667,
                    0.07754581421613693
                ],
                [
                    0.025758925825357437,
                    0.6648615598678589,
                    -0.7464885711669922,
                    -3.0093159675598145
                ],
                [
                    9.312824955642895e-10,
                    0.7467634081840515,
                    0.6650581359863281,
                    2.6810455322265625
                ],
                [
                    0.0,
                    0.0,
                    0.0,
                    1.0
                ]
            ]
        },
        {
            "file_path": "./train/r_89",
            "rotation": 0.06283185307179587,
            "transform_matrix": [
                [
                    0.0678536519408226,
                    -0.7473829984664917,
                    0.660887598991394,
                    2.6642329692840576
                ],
                [
                    0.9976522326469421,
                    0.050832007080316544,
                    -0.04494916647672653,
                    -0.18120336532592773
                ],
                [
                    3.725130204301763e-09,
                    0.6624384522438049,
                    0.7490825653076172,
                    3.01977276802063
                ],
                [
                    0.0,
                    0.0,
                    0.0,
                    1.0
                ]
            ]
        },
        {
            "file_path": "./train/r_90",
            "rotation": 0.06283185307179587,
            "transform_matrix": [
                [
                    -0.13526087999343872,
                    -0.6599156260490417,
                    0.7390294671058655,
                    2.979246139526367
                ],
                [
                    0.9907668232917786,
                    -0.09009262174367905,
                    0.10089334845542908,
                    0.40673089027404785
                ],
                [
                    7.4502626290495755e-09,
                    0.745911717414856,
                    0.6660129427909851,
                    2.6848950386047363
                ],
                [
                    0.0,
                    0.0,
                    0.0,
                    1.0
                ]
            ]
        },
        {
            "file_path": "./train/r_91",
            "rotation": 0.06283185307179587,
            "transform_matrix": [
                [
                    -0.3332028090953827,
                    -0.7440327405929565,
                    0.579092800617218,
                    2.334494113922119
                ],
                [
                    0.9428097605705261,
                    -0.26295205950737,
                    0.20465989410877228,
                    0.8250444531440735
                ],
                [
                    -1.4900523481742312e-08,
                    0.614216148853302,
                    0.7891027927398682,
                    3.1811065673828125
                ],
                [
                    0.0,
                    0.0,
                    0.0,
                    1.0
                ]
            ]
        },
        {
            "file_path": "./train/r_92",
            "rotation": 0.06283185307179587,
            "transform_matrix": [
                [
                    -0.59654301404953,
                    0.6778505444526672,
                    -0.42965641617774963,
                    -1.7320719957351685
                ],
                [
                    -0.8025276064872742,
                    -0.5038667917251587,
                    0.3193765878677368,
                    1.2875014543533325
                ],
                [
                    -1.4900520817207052e-08,
                    0.5353754162788391,
                    0.8445776104927063,
                    3.4047417640686035
                ],
                [
                    0.0,
                    0.0,
                    0.0,
                    1.0
                ]
            ]
        },
        {
            "file_path": "./train/r_93",
            "rotation": 0.06283185307179587,
            "transform_matrix": [
                [
                    -0.9553694725036621,
                    -0.13443626463413239,
                    0.2628914415836334,
                    1.0597929954528809
                ],
                [
                    0.2952684164047241,
                    -0.4349815249443054,
                    0.8506106734275818,
                    3.429062843322754
                ],
                [
                    0.0,
                    0.8903414607048035,
                    0.4552658498287201,
                    1.8353111743927002
                ],
                [
                    0.0,
                    0.0,
                    0.0,
                    1.0
                ]
            ]
        },
        {
            "file_path": "./train/r_94",
            "rotation": 0.06283185307179587,
            "transform_matrix": [
                [
                    0.5029951930046082,
                    0.5936712026596069,
                    -0.6280864477157593,
                    -2.5320019721984863
                ],
                [
                    -0.8642396926879883,
                    0.3455219268798828,
                    -0.3655518591403961,
                    -1.4736475944519043
                ],
                [
                    1.4900523481742312e-08,
                    0.7267455458641052,
                    0.686874508857727,
                    2.768994092941284
                ],
                [
                    0.0,
                    0.0,
                    0.0,
                    1.0
                ]
            ]
        },
        {
            "file_path": "./train/r_95",
            "rotation": 0.06283185307179587,
            "transform_matrix": [
                [
                    0.23811742663383484,
                    0.345496267080307,
                    -0.9076663851737976,
                    -3.659071445465088
                ],
                [
                    -0.9711923003196716,
                    0.08470895141363144,
                    -0.22254212200641632,
                    -0.8971330523490906
                ],
                [
                    -7.450261740871156e-09,
                    0.9345837235450745,
                    0.3557162582874298,
                    1.4339972734451294
                ],
                [
                    0.0,
                    0.0,
                    0.0,
                    1.0
                ]
            ]
        },
        {
            "file_path": "./train/r_96",
            "rotation": 0.06283185307179587,
            "transform_matrix": [
                [
                    0.8791295886039734,
                    -0.4611937701702118,
                    0.11984101682901382,
                    0.4831145405769348
                ],
                [
                    0.4764927625656128,
                    0.8509029150009155,
                    -0.22110676765441895,
                    -0.8913466930389404
                ],
                [
                    -7.450260852692736e-09,
                    0.2515046000480652,
                    0.9678157567977905,
                    3.9015512466430664
                ],
                [
                    0.0,
                    0.0,
                    0.0,
                    1.0
                ]
            ]
        },
        {
            "file_path": "./train/r_97",
            "rotation": 0.06283185307179587,
            "transform_matrix": [
                [
                    0.690095841884613,
                    -0.7149736881256104,
                    0.11195212602615356,
                    0.4513120949268341
                ],
                [
                    0.723658561706543,
                    0.6818137168884277,
                    -0.10675986856222153,
                    -0.43038058280944824
                ],
                [
                    0.0,
                    0.15470197796821594,
                    0.9879202246665955,
                    3.982598304748535
                ],
                [
                    0.0,
                    0.0,
                    0.0,
                    1.0
                ]
            ]
        },
        {
            "file_path": "./train/r_98",
            "rotation": 0.06283185307179587,
            "transform_matrix": [
                [
                    -0.4671463966369629,
                    0.6027068495750427,
                    -0.6468861103057861,
                    -2.6077890396118164
                ],
                [
                    -0.8841313719749451,
                    -0.31845083832740784,
                    0.3417937159538269,
                    1.3778713941574097
                ],
                [
                    -1.4900520817207052e-08,
                    0.7316579818725586,
                    0.6816397905349731,
                    2.7478911876678467
                ],
                [
                    0.0,
                    0.0,
                    0.0,
                    1.0
                ]
            ]
        },
        {
            "file_path": "./train/r_99",
            "rotation": 0.06283185307179587,
            "transform_matrix": [
                [
                    -0.19739872217178345,
                    -0.3855512738227844,
                    0.9012835025787354,
                    3.6333401203155518
                ],
                [
                    0.9802795052528381,
                    -0.07763839513063431,
                    0.18149131536483765,
                    0.7316451072692871
                ],
                [
                    0.0,
                    0.9194087386131287,
                    0.3932763636112213,
                    1.5854132175445557
                ],
                [
                    0.0,
                    0.0,
                    0.0,
                    1.0
                ]
            ]
        }
    ]
}