{
    "camera_angle_x": 0.6911112070083618,
    "frames": [
        {
            "file_path": "./train/r_0",
            "rotation": 0.06283185307179587,
            "transform_matrix": [
                [
                    -0.9862750172615051,
                    -0.1353958249092102,
                    0.0940488651394844,
                    0.3791387677192688
                ],
                [
                    0.16485083103179932,
                    -0.8100506067276001,
                    0.5626785755157471,
                    2.2683238983154297
                ],
                [
                    7.450260852692736e-09,
                    0.5705050230026245,
                    0.8212581276893616,
                    3.310734272003174
                ],
                [
                    0.0,
                    0.0,
                    0.0,
                    1.0
                ]
            ]
        },
        {
            "file_path": "./train/r_1",
            "rotation": 0.06283185307179587,
            "transform_matrix": [
                [
                    -0.9331726431846619,
                    -0.34630781412124634,
                    0.09582839161157608,
                    0.3863125443458557
                ],
                [
                    0.3593091666698456,
                    -0.8994064927101135,
                    0.24887880682945251,
                    1.0033040046691895
                ],
                [
                    -7.450260852692736e-09,
                    0.26670005917549133,
                    0.9637393951416016,
                    3.885118246078491
                ],
                [
                    0.0,
                    0.0,
                    0.0,
                    1.0
                ]
            ]
        },
        {
            "file_path": "./train/r_2",
            "rotation": 0.06283185307179587,
            "transform_matrix": [
                [
                    -0.7068369388580322,
                    0.26056599617004395,
                    -0.6575769782066345,
                    -2.6508872509002686
                ],
                [
                    -0.7073157429695129,
                    -0.26038962602615356,
                    0.6571319103240967,
                    2.649092674255371
                ],
                [
                    0.0,
                    0.929673433303833,
                    0.3683578670024872,
                    1.4849594831466675
                ],
                [
                    0.0,
                    0.0,
                    0.0,
                    1.0
                ]
            ]
        },
        {
            "file_path": "./train/r_3",
            "rotation": 0.06283185307179587,
            "transform_matrix": [
                [
                    -0.49142611026763916,
                    0.6733875274658203,
                    -0.55226731300354,
                    -2.2263524532318115
                ],
                [
                    -0.870870053768158,
                    -0.37998804450035095,
                    0.31164076924324036,
                    1.2563159465789795
                ],
                [
                    2.9801043410770944e-08,
                    0.6341515779495239,
                    0.7731742858886719,
                    3.1168935298919678
                ],
                [
                    0.0,
                    0.0,
                    0.0,
                    1.0
                ]
            ]
        },
        {
            "file_path": "./train/r_4",
            "rotation": 0.06283185307179587,
            "transform_matrix": [
                [
                    -0.33096930384635925,
                    -0.8127838969230652,
                    0.47938141226768494,
                    1.932527780532837
                ],
                [
                    0.9435960650444031,
                    -0.2850865423679352,
                    0.16814453899860382,
                    0.6778402328491211
                ],
                [
                    0.0,
                    0.5080332159996033,
                    0.8613004088401794,
                    3.472156047821045
                ],
                [
                    0.0,
                    0.0,
                    0.0,
                    1.0
                ]
            ]
        },
        {
            "file_path": "./train/r_5",
            "rotation": 0.06283185307179587,
            "transform_matrix": [
                [
                    0.6971325278282166,
                    0.11661761999130249,
                    -0.707335352897644,
                    -2.851477861404419
                ],
                [
                    -0.7168822884559631,
                    0.11340486258268356,
                    -0.6878485679626465,
                    -2.772920846939087
                ],
                [
                    0.0,
                    0.9866759777069092,
                    0.1626604050397873,
                    0.6557321548461914
                ],
                [
                    0.0,
                    0.0,
                    0.0,
                    1.0
                ]
            ]
        },
        {
            "file_path": "./train/r_6",
            "rotation": 0.06283185307179587,
            "transform_matrix": [
                [
                    -0.45556116104125977,
                    0.42002400755882263,
                    -0.7848396897315979,
                    -3.1639206409454346
                ],
                [
                    -0.8901562690734863,
                    -0.21495845913887024,
                    0.40166258811950684,
                    1.6192206144332886
                ],
                [
                    -1.4900521705385472e-08,
                    0.8816816806793213,
                    0.47181689739227295,
                    1.9020333290100098
                ],
                [
                    0.0,
                    0.0,
                    0.0,
                    1.0
                ]
            ]
        },
        {
            "file_path": "./train/r_7",
            "rotation": 0.06283185307179587,
            "transform_matrix": [
                [
                    0.4704893231391907,
                    0.844020426273346,
                    -0.25736716389656067,
                    -1.0375230312347412
                ],
                [
                    -0.8823570013046265,
                    0.45004749298095703,
                    -0.13723300397396088,
                    -0.5532267093658447
                ],
                [
                    0.0,
                    0.2916794717311859,
                    0.9564762115478516,
                    3.855837821960449
                ],
                [
                    0.0,
                    0.0,
                    0.0,
                    1.0
                ]
            ]
        },
        {
            "file_path": "./train/r_8",
            "rotation": 0.06283185307179587,
            "transform_matrix": [
                [
                    0.9643096923828125,
                    -0.16698549687862396,
                    0.20527829229831696,
                    0.8275374174118042
                ],
                [
                    0.2646149694919586,
                    0.6085283756256104,
                    -0.748075008392334,
                    -3.0157113075256348
                ],
                [
                    7.450261296781946e-09,
                    0.7757571339607239,
                    0.6310007572174072,
                    2.543750524520874
                ],
                [
                    0.0,
                    0.0,
                    0.0,
                    1.0
                ]
            ]
        },
        {
            "file_path": "./train/r_9",
            "rotation": 0.06283185307179587,
            "transform_matrix": [
                [
                    -0.750266969203949,
                    -0.12480755150318146,
                    0.649183452129364,
                    2.6170504093170166
                ],
                [
                    0.661069929599762,
                    -0.141647607088089,
                    0.73677659034729,
                    2.9701642990112305
                ],
                [
                    0.0,
                    0.9820127487182617,
                    0.18878130614757538,
                    0.7610331773757935
                ],
                [
                    0.0,
                    0.0,
                    0.0,
                    1.0
                ]
            ]
        },
        {
            "file_path": "./train/r_10",
            "rotation": 0.06283185307179587,
            "transform_matrix": [
                [
                    0.6128027439117432,
                    0.3936326205730438,
                    -0.6851668953895569,
                    -2.7621099948883057
                ],
                [
                    -0.7901816964149475,
                    0.3052704930305481,
                    -0.5313615202903748,
                    -2.142075300216675
                ],
                [
                    0.0,
                    0.8670946955680847,
                    0.4981151819229126,
                    2.008049249649048
                ],
                [
                    0.0,
                    0.0,
                    0.0,
                    1.0
                ]
            ]
        },
        {
            "file_path": "./train/r_11",
            "rotation": 0.06283185307179587,
            "transform_matrix": [
                [
                    -0.9999562501907349,
                    -0.00043079035822302103,
                    0.0012589633697643876,
                    0.005075253080576658
                ],
                [
                    0.0013306201435625553,
                    -0.32373741269111633,
                    0.9461064338684082,
                    3.8140344619750977
                ],
                [
                    0.0,
                    0.9461416006088257,
                    0.32372596859931946,
                    1.3050349950790405
                ],
                [
                    0.0,
                    0.0,
                    0.0,
                    1.0
                ]
            ]
        },
        {
            "file_path": "./train/r_12",
            "rotation": 0.06283185307179587,
            "transform_matrix": [
                [
                    0.9448989033699036,
                    -0.3089684844017029,
                    0.10782438516616821,
                    0.43467196822166443
                ],
                [
                    0.32723134756088257,
                    0.8921638131141663,
                    -0.31134894490242004,
                    -1.2551395893096924
                ],
                [
                    0.0,
                    0.3295029401779175,
                    0.9441149830818176,
                    3.80600643157959
                ],
                [
                    0.0,
                    0.0,
                    0.0,
                    1.0
                ]
            ]
        },
        {
            "file_path": "./train/r_13",
            "rotation": 0.06283185307179587,
            "transform_matrix": [
                [
                    0.2517344653606415,
                    -0.12800751626491547,
                    0.9592507481575012,
                    3.867023468017578
                ],
                [
                    0.9677520990371704,
                    0.033297695219516754,
                    -0.2495231032371521,
                    -1.0059014558792114
                ],
                [
                    -3.725130870435578e-09,
                    0.9912089705467224,
                    0.13226258754730225,
                    0.533189594745636
                ],
                [
                    0.0,
                    0.0,
                    0.0,
                    1.0
                ]
            ]
        },
        {
            "file_path": "./train/r_14",
            "rotation": 0.06283185307179587,
            "transform_matrix": [
                [
                    -0.9012336730957031,
                    -0.30852973461151123,
                    0.30415281653404236,
                    1.2261298894882202
                ],
                [
                    0.4332343637943268,
                    -0.6418174505233765,
                    0.6327124238014221,
                    2.5506505966186523
                ],
                [
                    0.0,
                    0.7020467519760132,
                    0.7120978832244873,
                    2.8706769943237305
                ],
                [
                    0.0,
                    0.0,
                    0.0,
                    1.0
                ]
            ]
        },
        {
            "file_path": "./train/r_15",
            "rotation": 0.06283185307179587,
            "transform_matrix": [
                [
                    -0.9669720530509949,
                    0.21757642924785614,
                    -0.132451593875885,
                    -0.5339515209197998
                ],
                [
                    -0.25471413135528564,
                    -0.8259860277175903,
                    0.5028263926506042,
                    2.0270416736602783
                ],
                [
                    0.0,
                    0.5199975371360779,
                    0.8541308641433716,
                    3.443253993988037
                ],
                [
                    0.0,
                    0.0,
                    0.0,
                    1.0
                ]
            ]
        },
        {
            "file_path": "./train/r_16",
            "rotation": 0.06283185307179587,
            "transform_matrix": [
                [
                    0.8569633364677429,
                    -0.31703680753707886,
                    0.4062313139438629,
                    1.6376384496688843
                ],
                [
                    0.5152941942214966,
                    0.5272501111030579,
                    -0.6755856275558472,
                    -2.723485231399536
                ],
                [
                    0.0,
                    0.7883431315422058,
                    0.6152053475379944,
                    2.480074405670166
                ],
                [
                    0.0,
                    0.0,
                    0.0,
                    1.0
                ]
            ]
        },
        {
            "file_path": "./train/r_17",
            "rotation": 0.06283185307179587,
            "transform_matrix": [
                [
                    -0.9835363030433655,
                    0.17947199940681458,
                    -0.019043628126382828,
                    -0.07677049934864044
                ],
                [
                    -0.180472731590271,
                    -0.978082537651062,
                    0.10378354787826538,
                    0.4183821678161621
                ],
                [
                    0.0,
                    0.10551972687244415,
                    0.994376003742218,
                    4.0086236000061035
                ],
                [
                    0.0,
                    0.0,
                    0.0,
                    1.0
                ]
            ]
        },
        {
            "file_path": "./train/r_18",
            "rotation": 0.06283185307179587,
            "transform_matrix": [
                [
                    0.9412407279014587,
                    -0.32768815755844116,
                    0.08129391819238663,
                    0.3277198076248169
                ],
                [
                    0.3376094102859497,
                    0.9135807156562805,
                    -0.22664399445056915,
                    -0.9136688709259033
                ],
                [
                    -7.450262184960366e-09,
                    0.24079127609729767,
                    0.970536470413208,
                    3.9125194549560547
                ],
                [
                    0.0,
                    0.0,
                    0.0,
                    1.0
                ]
            ]
        },
        {
            "file_path": "./train/r_19",
            "rotation": 0.06283185307179587,
            "transform_matrix": [
                [
                    -0.7936238050460815,
                    -0.5883466601371765,
                    0.15475769340991974,
                    0.6238738298416138
                ],
                [
                    0.6083382964134216,
                    -0.7675431370735168,
                    0.20189319550991058,
                    0.8138909935951233
                ],
                [
                    7.450260852692736e-09,
                    0.25439247488975525,
                    0.967060923576355,
                    3.898507595062256
                ],
                [
                    0.0,
                    0.0,
                    0.0,
                    1.0
                ]
            ]
        },
        {
            "file_path": "./train/r_20",
            "rotation": 0.06283185307179587,
            "transform_matrix": [
                [
                    -0.9752253293991089,
                    -0.20410014688968658,
                    0.08482955396175385,
                    0.3419729471206665
                ],
                [
                    0.22101978957653046,
                    -0.9005692601203918,
                    0.3743010461330414,
                    1.5089178085327148
                ],
                [
                    -7.450260852692736e-09,
                    0.38380730152130127,
                    0.9233744144439697,
                    3.7223944664001465
                ],
                [
                    0.0,
                    0.0,
                    0.0,
                    1.0
                ]
            ]
        },
        {
            "file_path": "./train/r_21",
            "rotation": 0.06283185307179587,
            "transform_matrix": [
                [
                    0.1778610199689865,
                    -0.636870265007019,
                    0.7501389384269714,
                    3.024031639099121
                ],
                [
                    0.9840121269226074,
                    0.11511483788490295,
                    -0.13558824360370636,
                    -0.5465962886810303
                ],
                [
                    0.0,
                    0.7623220086097717,
                    0.6471666693687439,
                    2.608920097351074
                ],
                [
                    0.0,
                    0.0,
                    0.0,
                    1.0
                ]
            ]
        },
        {
            "file_path": "./train/r_22",
            "rotation": 0.06283185307179587,
            "transform_matrix": [
                [
                    -0.5545235872268677,
                    0.46329566836357117,
                    -0.691225528717041,
                    -2.786534309387207
                ],
                [
                    -0.8321165442466736,
                    -0.30874085426330566,
                    0.46063366532325745,
                    1.8569504022598267
                ],
                [
                    1.4900523481742312e-08,
                    0.8306781053543091,
                    0.5567236542701721,
                    2.2443175315856934
                ],
                [
                    0.0,
                    0.0,
                    0.0,
                    1.0
                ]
            ]
        },
        {
            "file_path": "./train/r_23",
            "rotation": 0.06283185307179587,
            "transform_matrix": [
                [
                    -0.5404413938522339,
                    -0.6953529715538025,
                    0.4736654758453369,
                    1.9094854593276978
                ],
                [
                    0.8413307666778564,
                    -0.4466703534126282,
                    0.304266095161438,
                    1.2265864610671997
                ],
                [
                    0.0,
                    0.562991738319397,
                    0.8264264464378357,
                    3.331568956375122
                ],
                [
                    0.0,
                    0.0,
                    0.0,
                    1.0
                ]
            ]
        },
        {
            "file_path": "./train/r_24",
            "rotation": 0.06283185307179587,
            "transform_matrix": [
                [
                    0.8175819516181946,
                    -0.3182676136493683,
                    0.47977903485298157,
                    1.9341310262680054
                ],
                [
                    0.5757375955581665,
                    0.45195913314819336,
                    -0.6813151240348816,
                    -2.746582508087158
                ],
                [
                    0.0,
                    0.8333238959312439,
                    0.5527559518814087,
                    2.2283225059509277
                ],
                [
                    0.0,
                    0.0,
                    0.0,
                    1.0
                ]
            ]
        },
        {
            "file_path": "./train/r_25",
            "rotation": 0.06283185307179587,
            "transform_matrix": [
                [
                    -0.6366418600082397,
                    0.261955201625824,
                    -0.7252501249313354,
                    -2.9236974716186523
                ],
                [
                    -0.7711039781570435,
                    -0.21627646684646606,
                    0.5987838506698608,
                    2.413874387741089
                ],
                [
                    0.0,
                    0.9405285120010376,
                    0.3396875858306885,
                    1.3693809509277344
                ],
                [
                    0.0,
                    0.0,
                    0.0,
                    1.0
                ]
            ]
        },
        {
            "file_path": "./train/r_26",
            "rotation": 0.06283185307179587,
            "transform_matrix": [
                [
                    -0.3798421025276184,
                    -0.26533493399620056,
                    0.8861373662948608,
                    3.5722813606262207
                ],
                [
                    0.9250050783157349,
                    -0.10895656794309616,
                    0.36388155817985535,
                    1.4669140577316284
                ],
                [
                    -7.450261740871156e-09,
                    0.9579748511314392,
                    0.2868243157863617,
                    1.1562734842300415
                ],
                [
                    0.0,
                    0.0,
                    0.0,
                    1.0
                ]
            ]
        },
        {
            "file_path": "./train/r_27",
            "rotation": 0.06283185307179587,
            "transform_matrix": [
                [
                    -0.9097037315368652,
                    -0.3993035554885864,
                    0.11367574334144592,
                    0.45826050639152527
                ],
                [
                    0.41515466570854187,
                    -0.8749701976776123,
                    0.24909088015556335,
                    1.0041589736938477
                ],
                [
                    0.0,
                    0.2738134264945984,
                    0.961742639541626,
                    3.8770687580108643
                ],
                [
                    0.0,
                    0.0,
                    0.0,
                    1.0
                ]
            ]
        },
        {
            "file_path": "./train/r_28",
            "rotation": 0.06283185307179587,
            "transform_matrix": [
                [
                    -0.1895597279071808,
                    -0.6925143599510193,
                    0.6960195302963257,
                    2.8058602809906006
                ],
                [
                    0.9818255305290222,
                    -0.13370281457901,
                    0.1343795508146286,
                    0.5417236685752869
                ],
                [
                    7.450260852692736e-09,
                    0.7088987827301025,
                    0.7052775621414185,
                    2.84318208694458
                ],
                [
                    0.0,
                    0.0,
                    0.0,
                    1.0
                ]
            ]
        },
        {
            "file_path": "./train/r_29",
            "rotation": 0.06283185307179587,
            "transform_matrix": [
                [
                    -0.5946400761604309,
                    0.09987275302410126,
                    -0.7977126836776733,
                    -3.215815544128418
                ],
                [
                    -0.8039387464523315,
                    -0.07387173920869827,
                    0.5900349617004395,
                    2.378605365753174
                ],
                [
                    -7.450262184960366e-09,
                    0.992249071598053,
                    0.12421948462724686,
                    0.5007654428482056
                ],
                [
                    0.0,
                    0.0,
                    0.0,
                    1.0
                ]
            ]
        },
        {
            "file_path": "./train/r_30",
            "rotation": 0.06283185307179587,
            "transform_matrix": [
                [
                    -0.994683563709259,
                    0.02814364992082119,
                    -0.09862500429153442,
                    -0.39758649468421936
                ],
                [
                    -0.10256152600049973,
                    -0.27294865250587463,
                    0.9565055966377258,
                    3.855956554412842
                ],
                [
                    -1.862565435217789e-09,
                    0.9616115093231201,
                    0.27438580989837646,
                    1.1061302423477173
                ],
                [
                    0.0,
                    0.0,
                    0.0,
                    1.0
                ]
            ]
        },
        {
            "file_path": "./train/r_31",
            "rotation": 0.06283185307179587,
            "transform_matrix": [
                [
                    0.3983122706413269,
                    0.8798075914382935,
                    -0.25934338569641113,
                    -1.0454896688461304
                ],
                [
                    -0.9172031283378601,
                    0.3820725679397583,
                    -0.11262460798025131,
                    -0.45402300357818604
                ],
                [
                    0.0,
                    0.2827526032924652,
                    0.95915287733078,
                    3.8666281700134277
                ],
                [
                    0.0,
                    0.0,
                    0.0,
                    1.0
                ]
            ]
        },
        {
            "file_path": "./train/r_32",
            "rotation": 0.06283185307179587,
            "transform_matrix": [
                [
                    0.7061079740524292,
                    0.49466603994369507,
                    -0.5066070556640625,
                    -2.0422825813293457
                ],
                [
                    -0.70804363489151,
                    0.49331367015838623,
                    -0.5052220821380615,
                    -2.0366995334625244
                ],
                [
                    -1.4900521705385472e-08,
                    0.7154978513717651,
                    0.6985824108123779,
                    2.816192150115967
                ],
                [
                    0.0,
                    0.0,
                    0.0,
                    1.0
                ]
            ]
        },
        {
            "file_path": "./train/r_33",
            "rotation": 0.06283185307179587,
            "transform_matrix": [
                [
                    -0.61184161901474,
                    -0.3318495750427246,
                    0.7179482579231262,
                    2.894261598587036
                ],
                [
                    0.790925920009613,
                    -0.2567109763622284,
                    0.5553878545761108,
                    2.2389326095581055
                ],
                [
                    0.0,
                    0.9077252745628357,
                    0.4195377230644226,
                    1.6912806034088135
                ],
                [
                    0.0,
                    0.0,
                    0.0,
                    1.0
                ]
            ]
        },
        {
            "file_path": "./train/r_34",
            "rotation": 0.06283185307179587,
            "transform_matrix": [
                [
                    0.40851688385009766,
                    -0.6925976276397705,
                    0.5944526195526123,
                    2.396414279937744
                ],
                [
                    0.9127037525177002,
                    0.30999964475631714,
                    -0.2660709619522095,
                    -1.0726107358932495
                ],
                [
                    1.4900521705385472e-08,
                    0.6513051390647888,
                    0.7587816119194031,
                    3.058873176574707
                ],
                [
                    0.0,
                    0.0,
                    0.0,
                    1.0
                ]
            ]
        },
        {
            "file_path": "./train/r_35",
            "rotation": 0.06283185307179587,
            "transform_matrix": [
                [
                    -0.6473287343978882,
                    -0.6528175473213196,
                    0.39337214827537537,
                    1.5857990980148315
                ],
                [
                    0.7621545195579529,
                    -0.5544643998146057,
                    0.3341069221496582,
                    1.3468835353851318
                ],
                [
                    0.0,
                    0.5161282420158386,
                    0.8564743995666504,
                    3.4527010917663574
                ],
                [
                    0.0,
                    0.0,
                    0.0,
                    1.0
                ]
            ]
        },
        {
            "file_path": "./train/r_36",
            "rotation": 0.06283185307179587,
            "transform_matrix": [
                [
                    -0.9828827977180481,
                    0.14203092455863953,
                    -0.11698008328676224,
                    -0.47158128023147583
                ],
                [
                    -0.18399879336357117,
                    -0.7586992979049683,
                    0.6248829960823059,
                    2.51908802986145
                ],
                [
                    0.0,
                    0.6357613205909729,
                    0.7718511819839478,
                    3.111560106277466
                ],
                [
                    0.0,
                    0.0,
                    0.0,
                    1.0
                ]
            ]
        },
        {
            "file_path": "./train/r_37",
            "rotation": 0.06283185307179587,
            "transform_matrix": [
                [
                    -0.8823599815368652,
                    -0.38451769948005676,
                    0.2711319923400879,
                    1.093013048171997
                ],
                [
                    0.47048377990722656,
                    -0.7211365699768066,
                    0.5084894895553589,
                    2.0498709678649902
                ],
                [
                    0.0,
                    0.5762794613838196,
                    0.8172168731689453,
                    3.2944421768188477
                ],
                [
                    0.0,
                    0.0,
                    0.0,
                    1.0
                ]
            ]
        },
        {
            "file_path": "./train/r_38",
            "rotation": 0.06283185307179587,
            "transform_matrix": [
                [
                    -0.3503153324127197,
                    0.8716170191764832,
                    -0.34283363819122314,
                    -1.382063627243042
                ],
                [
                    -0.9365859627723694,
                    -0.3260147273540497,
                    0.12823157012462616,
                    0.5169393420219421
                ],
                [
                    7.450260408603526e-09,
                    0.36604371666908264,
                    0.9305585622787476,
                    3.751356363296509
                ],
                [
                    0.0,
                    0.0,
                    0.0,
                    1.0
                ]
            ]
        },
        {
            "file_path": "./train/r_39",
            "rotation": 0.06283185307179587,
            "transform_matrix": [
                [
                    -0.9352589845657349,
                    -0.35385656356811523,
                    0.00011010748858097941,
                    0.000443875789642334
                ],
                [
                    0.35384318232536316,
                    -0.9352941513061523,
                    0.0002910300681833178,
                    0.0011732280254364014
                ],
                [
                    7.275646231319488e-12,
                    0.0003830915957223624,
                    0.9999587535858154,
                    4.031128883361816
                ],
                [
                    0.0,
                    0.0,
                    0.0,
                    1.0
                ]
            ]
        },
        {
            "file_path": "./train/r_40",
            "rotation": 0.06283185307179587,
            "transform_matrix": [
                [
                    -0.34083762764930725,
                    0.7134885787963867,
                    -0.6121419072151184,
                    -2.4677248001098633
                ],
                [
                    -0.940076470375061,
                    -0.25868508219718933,
                    0.22194045782089233,
                    0.8947075605392456
                ],
                [
                    1.4900520817207052e-08,
                    0.6511574387550354,
                    0.7589085102081299,
                    3.059384346008301
                ],
                [
                    0.0,
                    0.0,
                    0.0,
                    1.0
                ]
            ]
        },
        {
            "file_path": "./train/r_41",
            "rotation": 0.06283185307179587,
            "transform_matrix": [
                [
                    0.06395398080348969,
                    0.46086621284484863,
                    -0.8851243257522583,
                    -3.56819748878479
                ],
                [
                    -0.9979098439216614,
                    0.029535965994000435,
                    -0.05672578886151314,
                    -0.22867842018604279
                ],
                [
                    1.8625653241954865e-09,
                    0.8869723081588745,
                    0.4617948830127716,
                    1.8616316318511963
                ],
                [
                    0.0,
                    0.0,
                    0.0,
                    1.0
                ]
            ]
        },
        {
            "file_path": "./train/r_42",
            "rotation": 0.06283185307179587,
            "transform_matrix": [
                [
                    0.4192112684249878,
                    -0.6571716070175171,
                    0.626366913318634,
                    2.5250699520111084
                ],
                [
                    0.9078415036201477,
                    0.30346015095710754,
                    -0.28923556208610535,
                    -1.1659940481185913
                ],
                [
                    0.0,
                    0.6899471879005432,
                    0.7238264083862305,
                    2.9179582595825195
                ],
                [
                    0.0,
                    0.0,
                    0.0,
                    1.0
                ]
            ]
        },
        {
            "file_path": "./train/r_43",
            "rotation": 0.06283185307179587,
            "transform_matrix": [
                [
                    0.9928098917007446,
                    0.05111540108919144,
                    -0.10784296691417694,
                    -0.4347468614578247
                ],
                [
                    -0.11934258788824081,
                    0.4252285659313202,
                    -0.897144615650177,
                    -3.616655111312866
                ],
                [
                    0.0,
                    0.9036359190940857,
                    0.4282741844654083,
                    1.7264997959136963
                ],
                [
                    0.0,
                    0.0,
                    0.0,
                    1.0
                ]
            ]
        },
        {
            "file_path": "./train/r_44",
            "rotation": 0.06283185307179587,
            "transform_matrix": [
                [
                    0.74677574634552,
                    -0.29049375653266907,
                    0.598214864730835,
                    2.411581039428711
                ],
                [
                    0.6650113463401794,
                    0.32621049880981445,
                    -0.6717665195465088,
                    -2.7080893516540527
                ],
                [
                    1.4900520817207052e-08,
                    0.8995498418807983,
                    0.4367906451225281,
                    1.7608320713043213
                ],
                [
                    0.0,
                    0.0,
                    0.0,
                    1.0
                ]
            ]
        },
        {
            "file_path": "./train/r_45",
            "rotation": 0.06283185307179587,
            "transform_matrix": [
                [
                    0.2757592797279358,
                    0.4607870280742645,
                    -0.8435429334640503,
                    -3.400570869445801
                ],
                [
                    -0.9611821174621582,
                    0.13219793140888214,
                    -0.24200907349586487,
                    -0.975610077381134
                ],
                [
                    -7.450260852692736e-09,
                    0.877604067325592,
                    0.4793582260608673,
                    1.9324345588684082
                ],
                [
                    0.0,
                    0.0,
                    0.0,
                    1.0
                ]
            ]
        },
        {
            "file_path": "./train/r_46",
            "rotation": 0.06283185307179587,
            "transform_matrix": [
                [
                    -0.8201109170913696,
                    -0.572040319442749,
                    0.011265954002737999,
                    0.04541638493537903
                ],
                [
                    0.5721294283866882,
                    -0.8199831247329712,
                    0.016149021685123444,
                    0.06510147452354431
                ],
                [
                    0.0,
                    0.01969030126929283,
                    0.9997648596763611,
                    4.0303473472595215
                ],
                [
                    0.0,
                    0.0,
                    0.0,
                    1.0
                ]
            ]
        },
        {
            "file_path": "./train/r_47",
            "rotation": 0.06283185307179587,
            "transform_matrix": [
                [
                    -0.1329701542854309,
                    -0.2157306671142578,
                    0.9673157930374146,
                    3.899535894393921
                ],
                [
                    0.9910767674446106,
                    -0.02894401177763939,
                    0.12978219985961914,
                    0.5231903791427612
                ],
                [
                    1.862565435217789e-09,
                    0.9760186672210693,
                    0.21765577793121338,
                    0.8774347901344299
                ],
                [
                    0.0,
                    0.0,
                    0.0,
                    1.0
                ]
            ]
        },
        {
            "file_path": "./train/r_48",
            "rotation": 0.06283185307179587,
            "transform_matrix": [
                [
                    0.9660109877586365,
                    0.19775810837745667,
                    -0.16622771322727203,
                    -0.6701130270957947
                ],
                [
                    -0.258334755897522,
                    0.7394919991493225,
                    -0.6215879917144775,
                    -2.505805015563965
                ],
                [
                    0.0,
                    0.6434541344642639,
                    0.7654502391815186,
                    3.0857560634613037
                ],
                [
                    0.0,
                    0.0,
                    0.0,
                    1.0
                ]
            ]
        },
        {
            "file_path": "./train/r_49",
            "rotation": 0.06283185307179587,
            "transform_matrix": [
                [
                    0.6635563969612122,
                    -0.7028419375419617,
                    0.2562386393547058,
                    1.0329736471176147
                ],
                [
                    0.7480690479278564,
                    0.6234387159347534,
                    -0.22729021310806274,
                    -0.9162740111351013
                ],
                [
                    0.0,
                    0.3425311744213104,
                    0.9394670128822327,
                    3.787269115447998
                ],
                [
                    0.0,
                    0.0,
                    0.0,
                    1.0
                ]
            ]
        },
        {
            "file_path": "./train/r_50",
            "rotation": 0.06283185307179587,
            "transform_matrix": [
                [
                    0.9537036418914795,
                    0.07754397392272949,
                    -0.2904326915740967,
                    -1.1708199977874756
                ],
                [
                    -0.30060523748397827,
                    0.24601693451404572,
                    -0.9214301705360413,
                    -3.714557409286499
                ],
                [
                    7.450260408603526e-09,
                    0.9661535024642944,
                    0.25793907046318054,
                    1.0398286581039429
                ],
                [
                    0.0,
                    0.0,
                    0.0,
                    1.0
                ]
            ]
        },
        {
            "file_path": "./train/r_51",
            "rotation": 0.06283185307179587,
            "transform_matrix": [
                [
                    -0.42706674337387085,
                    0.6481951475143433,
                    -0.6304001212120056,
                    -2.5413291454315186
                ],
                [
                    -0.9041726589202881,
                    -0.30616122484207153,
                    0.2977561056613922,
                    1.2003428936004639
                ],
                [
                    -1.4900522593563892e-08,
                    0.6972074508666992,
                    0.7168363332748413,
                    2.8897790908813477
                ],
                [
                    0.0,
                    0.0,
                    0.0,
                    1.0
                ]
            ]
        },
        {
            "file_path": "./train/r_52",
            "rotation": 0.06283185307179587,
            "transform_matrix": [
                [
                    0.5894528031349182,
                    -0.15033189952373505,
                    0.7936395406723022,
                    3.199395179748535
                ],
                [
                    0.8077497482299805,
                    0.10970423370599747,
                    -0.5791559219360352,
                    -2.3347485065460205
                ],
                [
                    0.0,
                    0.9825249314308167,
                    0.18609726428985596,
                    0.7502130270004272
                ],
                [
                    0.0,
                    0.0,
                    0.0,
                    1.0
                ]
            ]
        },
        {
            "file_path": "./train/r_53",
            "rotation": 0.06283185307179587,
            "transform_matrix": [
                [
                    0.9423484206199646,
                    -0.2961854636669159,
                    0.15548214316368103,
                    0.6267944574356079
                ],
                [
                    0.3345053195953369,
                    0.8343960642814636,
                    -0.4380149841308594,
                    -1.7657678127288818
                ],
                [
                    -1.4900522593563892e-08,
                    0.4648091197013855,
                    0.885373055934906,
                    3.5692005157470703
                ],
                [
                    0.0,
                    0.0,
                    0.0,
                    1.0
                ]
            ]
        },
        {
            "file_path": "./train/r_54",
            "rotation": 0.06283185307179587,
            "transform_matrix": [
                [
                    0.9476007223129272,
                    -0.12669141590595245,
                    0.2931174337863922,
                    1.1816428899765015
                ],
                [
                    0.319322794675827,
                    0.3759608864784241,
                    -0.8698354363441467,
                    -3.506563663482666
                ],
                [
                    0.0,
                    0.9179285168647766,
                    0.3967188596725464,
                    1.5992909669876099
                ],
                [
                    0.0,
                    0.0,
                    0.0,
                    1.0
                ]
            ]
        },
        {
            "file_path": "./train/r_55",
            "rotation": 0.06283185307179587,
            "transform_matrix": [
                [
                    -0.5447617173194885,
                    -0.8220518231391907,
                    0.16562335193157196,
                    0.6676766276359558
                ],
                [
                    0.8385397791862488,
                    -0.5340501666069031,
                    0.10759805887937546,
                    0.43375954031944275
                ],
                [
                    -7.450260852692736e-09,
                    0.19751271605491638,
                    0.9802597165107727,
                    3.951716184616089
                ],
                [
                    0.0,
                    0.0,
                    0.0,
                    1.0
                ]
            ]
        },
        {
            "file_path": "./train/r_56",
            "rotation": 0.06283185307179587,
            "transform_matrix": [
                [
                    0.9463791847229004,
                    -0.19639617204666138,
                    0.25634464621543884,
                    1.0334010124206543
                ],
                [
                    0.3229255676269531,
                    0.5755668878555298,
                    -0.7512542605400085,
                    -3.0285279750823975
                ],
                [
                    -1.4900524369920731e-08,
                    0.7938143610954285,
                    0.6081297993659973,
                    2.4515507221221924
                ],
                [
                    0.0,
                    0.0,
                    0.0,
                    1.0
                ]
            ]
        },
        {
            "file_path": "./train/r_57",
            "rotation": 0.06283185307179587,
            "transform_matrix": [
                [
                    0.3616980314254761,
                    -0.4902573823928833,
                    0.792941689491272,
                    3.196582317352295
                ],
                [
                    0.9322492480278015,
                    0.19021214544773102,
                    -0.3076489269733429,
                    -1.2402236461639404
                ],
                [
                    0.0,
                    0.8505627512931824,
                    0.5258449912071228,
                    2.1198363304138184
                ],
                [
                    0.0,
                    0.0,
                    0.0,
                    1.0
                ]
            ]
        },
        {
            "file_path": "./train/r_58",
            "rotation": 0.06283185307179587,
            "transform_matrix": [
                [
                    0.33307239413261414,
                    -0.7851645946502686,
                    0.5220548510551453,
                    2.104557514190674
                ],
                [
                    0.9428557753562927,
                    0.2773665487766266,
                    -0.184420645236969,
                    -0.743454098701477
                ],
                [
                    0.0,
                    0.553691565990448,
                    0.8326855301856995,
                    3.3568012714385986
                ],
                [
                    0.0,
                    0.0,
                    0.0,
                    1.0
                ]
            ]
        },
        {
            "file_path": "./train/r_59",
            "rotation": 0.06283185307179587,
            "transform_matrix": [
                [
                    -0.6731275320053101,
                    0.41192111372947693,
                    -0.6141242384910583,
                    -2.4757163524627686
                ],
                [
                    -0.7394684553146362,
                    -0.3749658763408661,
                    0.5590285658836365,
                    2.2536091804504395
                ],
                [
                    1.4900522593563892e-08,
                    0.8304887413978577,
                    0.5570061802864075,
                    2.2454564571380615
                ],
                [
                    0.0,
                    0.0,
                    0.0,
                    1.0
                ]
            ]
        },
        {
            "file_path": "./train/r_60",
            "rotation": 0.06283185307179587,
            "transform_matrix": [
                [
                    -0.35144519805908203,
                    0.7432774305343628,
                    -0.5691942572593689,
                    -2.2945899963378906
                ],
                [
                    -0.9361626505851746,
                    -0.2790340781211853,
                    0.21368145942687988,
                    0.8614130616188049
                ],
                [
                    1.4900522593563892e-08,
                    0.6080037951469421,
                    0.7938989400863647,
                    3.2004411220550537
                ],
                [
                    0.0,
                    0.0,
                    0.0,
                    1.0
                ]
            ]
        },
        {
            "file_path": "./train/r_61",
            "rotation": 0.06283185307179587,
            "transform_matrix": [
                [
                    0.9609926342964172,
                    0.23558636009693146,
                    -0.14460580050945282,
                    -0.5829487442970276
                ],
                [
                    -0.27641910314559937,
                    0.8190343976020813,
                    -0.5027334690093994,
                    -2.0266671180725098
                ],
                [
                    -7.450261740871156e-09,
                    0.5231363773345947,
                    0.852212131023407,
                    3.435518980026245
                ],
                [
                    0.0,
                    0.0,
                    0.0,
                    1.0
                ]
            ]
        },
        {
            "file_path": "./train/r_62",
            "rotation": 0.06283185307179587,
            "transform_matrix": [
                [
                    0.1650560349225998,
                    -0.6636609435081482,
                    0.729561448097229,
                    2.941077709197998
                ],
                [
                    0.9862406253814697,
                    0.11106950044631958,
                    -0.12209852784872055,
                    -0.49221521615982056
                ],
                [
                    0.0,
                    0.7397348284721375,
                    0.6728665828704834,
                    2.712523937225342
                ],
                [
                    0.0,
                    0.0,
                    0.0,
                    1.0
                ]
            ]
        },
        {
            "file_path": "./train/r_63",
            "rotation": 0.06283185307179587,
            "transform_matrix": [
                [
                    -0.41047385334968567,
                    0.4189501404762268,
                    -0.8098899126052856,
                    -3.2649052143096924
                ],
                [
                    -0.9118253588676453,
                    -0.18859760463237762,
                    0.364585816860199,
                    1.4697531461715698
                ],
                [
                    0.0,
                    0.8882013559341431,
                    0.4594268202781677,
                    1.8520851135253906
                ],
                [
                    0.0,
                    0.0,
                    0.0,
                    1.0
                ]
            ]
        },
        {
            "file_path": "./train/r_64",
            "rotation": 0.06283185307179587,
            "transform_matrix": [
                [
                    -0.3099255859851837,
                    -0.8457437753677368,
                    0.434318482875824,
                    1.750866174697876
                ],
                [
                    0.9507156610488892,
                    -0.27570563554763794,
                    0.1415843367576599,
                    0.5707682371139526
                ],
                [
                    -7.450260852692736e-09,
                    0.4568302631378174,
                    0.8895159959793091,
                    3.5859017372131348
                ],
                [
                    0.0,
                    0.0,
                    0.0,
                    1.0
                ]
            ]
        },
        {
            "file_path": "./train/r_65",
            "rotation": 0.06283185307179587,
            "transform_matrix": [
                [
                    -0.7573075294494629,
                    -0.3585599362850189,
                    0.5457518100738525,
                    2.200086832046509
                ],
                [
                    0.6529927253723145,
                    -0.41583940386772156,
                    0.6329349875450134,
                    2.5515477657318115
                ],
                [
                    0.0,
                    0.8357645273208618,
                    0.5490589737892151,
                    2.21341872215271
                ],
                [
                    0.0,
                    0.0,
                    0.0,
                    1.0
                ]
            ]
        },
        {
            "file_path": "./train/r_66",
            "rotation": 0.06283185307179587,
            "transform_matrix": [
                [
                    -0.5260447859764099,
                    0.8244104385375977,
                    -0.20878277719020844,
                    -0.8416650891304016
                ],
                [
                    -0.8504064083099365,
                    -0.5099641680717468,
                    0.1291489452123642,
                    0.520637571811676
                ],
                [
                    0.0,
                    0.24550771713256836,
                    0.9693542122840881,
                    3.9077532291412354
                ],
                [
                    0.0,
                    0.0,
                    0.0,
                    1.0
                ]
            ]
        },
        {
            "file_path": "./train/r_67",
            "rotation": 0.06283185307179587,
            "transform_matrix": [
                [
                    -0.942812979221344,
                    0.33303433656692505,
                    -0.01070069707930088,
                    -0.04313766956329346
                ],
                [
                    -0.3331936001777649,
                    -0.942362368106842,
                    0.030278963968157768,
                    0.12206342816352844
                ],
                [
                    0.0,
                    0.03211513161659241,
                    0.9994429349899292,
                    4.029049396514893
                ],
                [
                    0.0,
                    0.0,
                    0.0,
                    1.0
                ]
            ]
        },
        {
            "file_path": "./train/r_68",
            "rotation": 0.06283185307179587,
            "transform_matrix": [
                [
                    0.279472291469574,
                    -0.9569237232208252,
                    0.07858629524707794,
                    0.31680455803871155
                ],
                [
                    0.9601090550422668,
                    0.278545081615448,
                    -0.022875206544995308,
                    -0.09221670031547546
                ],
                [
                    0.0,
                    0.08185072988271713,
                    0.9966034293174744,
                    4.017602443695068
                ],
                [
                    0.0,
                    0.0,
                    0.0,
                    1.0
                ]
            ]
        },
        {
            "file_path": "./train/r_69",
            "rotation": 0.06283185307179587,
            "transform_matrix": [
                [
                    -0.5152220726013184,
                    0.8283527493476868,
                    -0.21987302601337433,
                    -0.8863731622695923
                ],
                [
                    -0.8570066690444946,
                    -0.49799567461013794,
                    0.13218502700328827,
                    0.5328768491744995
                ],
                [
                    0.0,
                    0.2565576136112213,
                    0.9664886593818665,
                    3.8962013721466064
                ],
                [
                    0.0,
                    0.0,
                    0.0,
                    1.0
                ]
            ]
        },
        {
            "file_path": "./train/r_70",
            "rotation": 0.06283185307179587,
            "transform_matrix": [
                [
                    0.20026302337646484,
                    0.1869032382965088,
                    -0.9617076516151428,
                    -3.8769278526306152
                ],
                [
                    -0.9796983599662781,
                    0.03820544481277466,
                    -0.1965854912996292,
                    -0.7924942374229431
                ],
                [
                    0.0,
                    0.9816300272941589,
                    0.19076119363307953,
                    0.7690147757530212
                ],
                [
                    0.0,
                    0.0,
                    0.0,
                    1.0
                ]
            ]
        },
        {
            "file_path": "./train/r_71",
            "rotation": 0.06283185307179587,
            "transform_matrix": [
                [
                    0.421364963054657,
                    -0.8426932096481323,
                    0.335094153881073,
                    1.3508634567260742
                ],
                [
                    0.9068437814712524,
                    0.39155739545822144,
                    -0.15570150315761566,
                    -0.6276787519454956
                ],
                [
                    0.0,
                    0.3695143461227417,
                    0.9291859269142151,
                    3.7458226680755615
                ],
                [
                    0.0,
                    0.0,
                    0.0,
                    1.0
                ]
            ]
        },
        {
            "file_path": "./train/r_72",
            "rotation": 0.06283185307179587,
            "transform_matrix": [
                [
                    0.3551884889602661,
                    0.13349619507789612,
                    -0.9251692295074463,
                    -3.729630470275879
                ],
                [
                    -0.9347487688064575,
                    0.050726260989904404,
                    -0.3515484631061554,
                    -1.4171956777572632
                ],
                [
                    -3.725130204301763e-09,
                    0.9897451996803284,
                    0.14280372858047485,
                    0.5756840109825134
                ],
                [
                    0.0,
                    0.0,
                    0.0,
                    1.0
                ]
            ]
        },
        {
            "file_path": "./train/r_73",
            "rotation": 0.06283185307179587,
            "transform_matrix": [
                [
                    -0.24498745799064636,
                    -0.8800302743911743,
                    0.40681833028793335,
                    1.6400048732757568
                ],
                [
                    0.9694820642471313,
                    -0.222383052110672,
                    0.10280271619558334,
                    0.41442811489105225
                ],
                [
                    7.450261740871156e-09,
                    0.41962164640426636,
                    0.9076606035232544,
                    3.659048080444336
                ],
                [
                    0.0,
                    0.0,
                    0.0,
                    1.0
                ]
            ]
        },
        {
            "file_path": "./train/r_74",
            "rotation": 0.06283185307179587,
            "transform_matrix": [
                [
                    0.03272046148777008,
                    -0.1926419734954834,
                    0.9806826710700989,
                    3.9534215927124023
                ],
                [
                    0.9994216561317444,
                    0.006306981202214956,
                    -0.03210695832967758,
                    -0.12943263351917267
                ],
                [
                    0.0,
                    0.9812437295913696,
                    0.19273819029331207,
                    0.7769845724105835
                ],
                [
                    0.0,
                    0.0,
                    0.0,
                    1.0
                ]
            ]
        },
        {
            "file_path": "./train/r_75",
            "rotation": 0.06283185307179587,
            "transform_matrix": [
                [
                    0.44021931290626526,
                    -0.3877820074558258,
                    0.8097899556159973,
                    3.26450252532959
                ],
                [
                    0.897842526435852,
                    0.19013258814811707,
                    -0.39704644680023193,
                    -1.6006114482879639
                ],
                [
                    0.0,
                    0.9019228219985962,
                    0.4318700134754181,
                    1.7409956455230713
                ],
                [
                    0.0,
                    0.0,
                    0.0,
                    1.0
                ]
            ]
        },
        {
            "file_path": "./train/r_76",
            "rotation": 0.06283185307179587,
            "transform_matrix": [
                [
                    0.5246914625167847,
                    0.1602783352136612,
                    -0.8360192179679871,
                    -3.3702404499053955
                ],
                [
                    -0.8512420654296875,
                    0.09879288822412491,
                    -0.5153083205223083,
                    -2.077360153198242
                ],
                [
                    -7.450260852692736e-09,
                    0.9821103811264038,
                    0.18827266991138458,
                    0.7589827179908752
                ],
                [
                    0.0,
                    0.0,
                    0.0,
                    1.0
                ]
            ]
        },
        {
            "file_path": "./train/r_77",
            "rotation": 0.06283185307179587,
            "transform_matrix": [
                [
                    -0.8426721692085266,
                    -0.42362532019615173,
                    0.33222496509552,
                    1.3392969369888306
                ],
                [
                    0.5383474230766296,
                    -0.6630983352661133,
                    0.5200299024581909,
                    2.0963940620422363
                ],
                [
                    0.0,
                    0.6171159744262695,
                    0.7868372797966003,
                    3.171973466873169
                ],
                [
                    0.0,
                    0.0,
                    0.0,
                    1.0
                ]
            ]
        },
        {
            "file_path": "./train/r_78",
            "rotation": 0.06283185307179587,
            "transform_matrix": [
                [
                    0.961036205291748,
                    0.043139949440956116,
                    -0.27287864685058594,
                    -1.1000542640686035
                ],
                [
                    -0.2762669026851654,
                    0.15006884932518005,
                    -0.9492496252059937,
                    -3.82670521736145
                ],
                [
                    0.0,
                    0.9877288341522217,
                    0.1561407893896103,
                    0.6294496059417725
                ],
                [
                    0.0,
                    0.0,
                    0.0,
                    1.0
                ]
            ]
        },
        {
            "file_path": "./train/r_79",
            "rotation": 0.06283185307179587,
            "transform_matrix": [
                [
                    0.7403754591941833,
                    0.37496688961982727,
                    -0.5578259229660034,
                    -2.2487611770629883
                ],
                [
                    -0.6721296310424805,
                    0.41303977370262146,
                    -0.6144657135009766,
                    -2.477092981338501
                ],
                [
                    0.0,
                    0.829932451248169,
                    0.5578345656394958,
                    2.248795986175537
                ],
                [
                    0.0,
                    0.0,
                    0.0,
                    1.0
                ]
            ]
        },
        {
            "file_path": "./train/r_80",
            "rotation": 0.06283185307179587,
            "transform_matrix": [
                [
                    0.07581541687250137,
                    -0.952948272228241,
                    0.293470174074173,
                    1.1830650568008423
                ],
                [
                    0.9970788359642029,
                    0.07245983183383942,
                    -0.02231474779546261,
                    -0.0899573415517807
                ],
                [
                    0.0,
                    0.2943280339241028,
                    0.9556645154953003,
                    3.8525660037994385
                ],
                [
                    0.0,
                    0.0,
                    0.0,
                    1.0
                ]
            ]
        },
        {
            "file_path": "./train/r_81",
            "rotation": 0.06283185307179587,
            "transform_matrix": [
                [
                    0.36681827902793884,
                    0.8517653942108154,
                    -0.3740450143814087,
                    -1.5078860521316528
                ],
                [
                    -0.9302464127540588,
                    0.3358713388442993,
                    -0.147494837641716,
                    -0.5945952534675598
                ],
                [
                    1.4900520817207052e-08,
                    0.4020897448062897,
                    0.9155614972114563,
                    3.690899133682251
                ],
                [
                    0.0,
                    0.0,
                    0.0,
                    1.0
                ]
            ]
        },
        {
            "file_path": "./train/r_82",
            "rotation": 0.06283185307179587,
            "transform_matrix": [
                [
                    -0.9494878649711609,
                    -0.1869554966688156,
                    0.25186818838119507,
                    1.015355110168457
                ],
                [
                    0.3136671483516693,
                    -0.5659245848655701,
                    0.7624189257621765,
                    3.073535919189453
                ],
                [
                    -1.4900523481742312e-08,
                    0.8029738664627075,
                    0.5959842801094055,
                    2.402588367462158
                ],
                [
                    0.0,
                    0.0,
                    0.0,
                    1.0
                ]
            ]
        },
        {
            "file_path": "./train/r_83",
            "rotation": 0.06283185307179587,
            "transform_matrix": [
                [
                    -0.2869504690170288,
                    0.830743670463562,
                    -0.47696083784103394,
                    -1.9227700233459473
                ],
                [
                    -0.9579006433486938,
                    -0.24885907769203186,
                    0.14287926256656647,
                    0.5759885311126709
                ],
                [
                    7.450261740871156e-09,
                    0.4979197084903717,
                    0.8671857714653015,
                    3.495882034301758
                ],
                [
                    0.0,
                    0.0,
                    0.0,
                    1.0
                ]
            ]
        },
        {
            "file_path": "./train/r_84",
            "rotation": 0.06283185307179587,
            "transform_matrix": [
                [
                    0.9681189656257629,
                    -0.15762031078338623,
                    0.19446712732315063,
                    0.783954381942749
                ],
                [
                    0.2503190338611603,
                    0.6096029877662659,
                    -0.7521095275878906,
                    -3.031975507736206
                ],
                [
                    0.0,
                    0.7768718004226685,
                    0.6296278834342957,
                    2.5382158756256104
                ],
                [
                    0.0,
                    0.0,
                    0.0,
                    1.0
                ]
            ]
        },
        {
            "file_path": "./train/r_85",
            "rotation": 0.06283185307179587,
            "transform_matrix": [
                [
                    0.0245951060205698,
                    0.2760978937149048,
                    -0.9607747197151184,
                    -3.873166561126709
                ],
                [
                    -0.9996545910835266,
                    0.0067930035293102264,
                    -0.023638522252440453,
                    -0.09529385715723038
                ],
                [
                    4.65641303293296e-10,
                    0.9611002802848816,
                    0.27617147564888,
                    1.1133286952972412
                ],
                [
                    0.0,
                    0.0,
                    0.0,
                    1.0
                ]
            ]
        },
        {
            "file_path": "./train/r_86",
            "rotation": 0.06283185307179587,
            "transform_matrix": [
                [
                    0.8549296855926514,
                    -0.36958077549934387,
                    0.3639097213745117,
                    1.4670276641845703
                ],
                [
                    0.5186612010002136,
                    0.6091945171356201,
                    -0.5998466610908508,
                    -2.418159246444702
                ],
                [
                    -1.4900522593563892e-08,
                    0.7016280293464661,
                    0.7125102877616882,
                    2.8723397254943848
                ],
                [
                    0.0,
                    0.0,
                    0.0,
                    1.0
                ]
            ]
        },
        {
            "file_path": "./train/r_87",
            "rotation": 0.06283185307179587,
            "transform_matrix": [
                [
                    -0.047411248087882996,
                    0.22011566162109375,
                    -0.9742803573608398,
                    -3.927611827850342
                ],
                [
                    -0.9988325238227844,
                    -0.010448156856000423,
                    0.046245839446783066,
                    0.1864306479692459
                ],
                [
                    0.0,
                    0.9754126667976379,
                    0.22035549581050873,
                    0.8883181214332581
                ],
                [
                    0.0,
                    0.0,
                    0.0,
                    1.0
                ]
            ]
        },
        {
            "file_path": "./train/r_88",
            "rotation": 0.06283185307179587,
            "transform_matrix": [
                [
                    0.20896625518798828,
                    -0.8766987919807434,
                    0.43324992060661316,
                    1.7465585470199585
                ],
                [
                    0.9778789281845093,
                    0.1873447448015213,
                    -0.09258265048265457,
                    -0.3732280135154724
                ],
                [
                    0.0,
                    0.4430476725101471,
                    0.8964599370956421,
                    3.6138947010040283
                ],
                [
                    0.0,
                    0.0,
                    0.0,
                    1.0
                ]
            ]
        },
        {
            "file_path": "./train/r_89",
            "rotation": 0.06283185307179587,
            "transform_matrix": [
                [
                    -0.0039041214622557163,
                    0.431436151266098,
                    -0.9020968675613403,
                    -3.6366183757781982
                ],
                [
                    -0.9999493360519409,
                    -0.00168446428142488,
                    0.003522074082866311,
                    0.014198518358170986
                ],
                [
                    1.1641029806774839e-10,
                    0.9021363258361816,
                    0.4314238131046295,
                    1.739196538925171
                ],
                [
                    0.0,
                    0.0,
                    0.0,
                    1.0
                ]
            ]
        },
        {
            "file_path": "./train/r_90",
            "rotation": 0.06283185307179587,
            "transform_matrix": [
                [
                    -0.9609100222587585,
                    0.24530744552612305,
                    -0.12804292142391205,
                    -0.5161788463592529
                ],
                [
                    -0.27670586109161377,
                    -0.8518735766410828,
                    0.44465172290802,
                    1.7925224304199219
                ],
                [
                    -7.450261296781946e-09,
                    0.4627370238304138,
                    0.8864577412605286,
                    3.573572874069214
                ],
                [
                    0.0,
                    0.0,
                    0.0,
                    1.0
                ]
            ]
        },
        {
            "file_path": "./train/r_91",
            "rotation": 0.06283185307179587,
            "transform_matrix": [
                [
                    0.2617824375629425,
                    -0.25505536794662476,
                    0.9307730793952942,
                    3.7522213459014893
                ],
                [
                    0.9650825262069702,
                    0.06918476521968842,
                    -0.2524758577346802,
                    -1.017804741859436
                ],
                [
                    0.0,
                    0.9644429087638855,
                    0.26426252722740173,
                    1.0653202533721924
                ],
                [
                    0.0,
                    0.0,
                    0.0,
                    1.0
                ]
            ]
        },
        {
            "file_path": "./train/r_92",
            "rotation": 0.06283185307179587,
            "transform_matrix": [
                [
                    0.4793945252895355,
                    0.8580954074859619,
                    -0.18391145765781403,
                    -0.7414014339447021
                ],
                [
                    -0.8775507211685181,
                    0.46876630187034607,
                    -0.10046842694282532,
                    -0.4050179123878479
                ],
                [
                    0.0,
                    0.20957212150096893,
                    0.9777525067329407,
                    3.9416093826293945
                ],
                [
                    0.0,
                    0.0,
                    0.0,
                    1.0
                ]
            ]
        },
        {
            "file_path": "./train/r_93",
            "rotation": 0.06283185307179587,
            "transform_matrix": [
                [
                    -0.1093023493885994,
                    0.9644313454627991,
                    -0.2406451404094696,
                    -0.970111608505249
                ],
                [
                    -0.9939653277397156,
                    -0.10605461895465851,
                    0.026462772861123085,
                    0.10667924582958221
                ],
                [
                    0.0,
                    0.24210458993911743,
                    0.9702098369598389,
                    3.9112021923065186
                ],
                [
                    0.0,
                    0.0,
                    0.0,
                    1.0
                ]
            ]
        },
        {
            "file_path": "./train/r_94",
            "rotation": 0.06283185307179587,
            "transform_matrix": [
                [
                    -0.29459822177886963,
                    0.6255432963371277,
                    -0.7223938703536987,
                    -2.9121832847595215
                ],
                [
                    -0.9555763602256775,
                    -0.19285106658935547,
                    0.222709521651268,
                    0.8978078365325928
                ],
                [
                    1.4900523481742312e-08,
                    0.755972146987915,
                    0.6545723080635071,
                    2.6387743949890137
                ],
                [
                    0.0,
                    0.0,
                    0.0,
                    1.0
                ]
            ]
        },
        {
            "file_path": "./train/r_95",
            "rotation": 0.06283185307179587,
            "transform_matrix": [
                [
                    0.9609121084213257,
                    0.22347742319107056,
                    -0.1631680130958557,
                    -0.6577785015106201
                ],
                [
                    -0.2766985595226288,
                    0.7760870456695557,
                    -0.5666459798812866,
                    -2.2843174934387207
                ],
                [
                    0.0,
                    0.5896921157836914,
                    0.8075926899909973,
                    3.2556447982788086
                ],
                [
                    0.0,
                    0.0,
                    0.0,
                    1.0
                ]
            ]
        },
        {
            "file_path": "./train/r_96",
            "rotation": 0.06283185307179587,
            "transform_matrix": [
                [
                    -0.5846544504165649,
                    0.5579625368118286,
                    -0.5888936519622803,
                    -2.374004364013672
                ],
                [
                    -0.811229407787323,
                    -0.4021245837211609,
                    0.424416720867157,
                    1.710949182510376
                ],
                [
                    1.4900520817207052e-08,
                    0.7259224653244019,
                    0.6877442002296448,
                    2.7725002765655518
                ],
                [
                    0.0,
                    0.0,
                    0.0,
                    1.0
                ]
            ]
        },
        {
            "file_path": "./train/r_97",
            "rotation": 0.06283185307179587,
            "transform_matrix": [
                [
                    0.9352949857711792,
                    -0.25061818957328796,
                    0.24966572225093842,
                    1.0064762830734253
                ],
                [
                    0.35374778509140015,
                    0.6626244783401489,
                    -0.6601061820983887,
                    -2.6610829830169678
                ],
                [
                    0.0,
                    0.7057685852050781,
                    0.7084096670150757,
                    2.855808734893799
                ],
                [
                    0.0,
                    0.0,
                    0.0,
                    1.0
                ]
            ]
        },
        {
            "file_path": "./train/r_98",
            "rotation": 0.06283185307179587,
            "transform_matrix": [
                [
                    -0.9007003307342529,
                    0.4073580801486969,
                    -0.15074890851974487,
                    -0.6077133417129517
                ],
                [
                    -0.43434232473373413,
                    -0.8447428345680237,
                    0.31260961294174194,
                    1.2602217197418213
                ],
                [
                    0.0,
                    0.34707170724868774,
                    0.9377992749214172,
                    3.780545711517334
                ],
                [
                    0.0,
                    0.0,
                    0.0,
                    1.0
                ]
            ]
        },
        {
            "file_path": "./train/r_99",
            "rotation": 0.06283185307179587,
            "transform_matrix": [
                [
                    0.9601772427558899,
                    -0.27425962686538696,
                    0.0525476448237896,
                    0.2118350714445114
                ],
                [
                    0.2792380452156067,
                    0.9430586695671082,
                    -0.18068833649158478,
                    -0.7284080386161804
                ],
                [
                    0.0,
                    0.18818092346191406,
                    0.9820936322212219,
                    3.9591095447540283
                ],
                [
                    0.0,
                    0.0,
                    0.0,
                    1.0
                ]
            ]
        }
    ]
}